{
"meta":{"test_sets":[],"test_metrics":[],"learn_metrics":[{"best_value":"Min","name":"Logloss"}],"launch_mode":"Train","parameters":"","iteration_count":1000,"learn_sets":["learn"],"name":"experiment"},
"iterations":[
{"learn":[0.6855021468],"iteration":0,"passed_time":0.01804442081,"remaining_time":18.02637638},
{"learn":[0.6786382486],"iteration":1,"passed_time":0.02985595652,"remaining_time":14.8981223},
{"learn":[0.6720160265],"iteration":2,"passed_time":0.04182806573,"remaining_time":13.90086051},
{"learn":[0.6656769109],"iteration":3,"passed_time":0.05346133816,"remaining_time":13.3118732},
{"learn":[0.6590787818],"iteration":4,"passed_time":0.06591907706,"remaining_time":13.11789634},
{"learn":[0.653154519],"iteration":5,"passed_time":0.07768141208,"remaining_time":12.8692206},
{"learn":[0.6470880072],"iteration":6,"passed_time":0.08985839537,"remaining_time":12.74705523},
{"learn":[0.6417143969],"iteration":7,"passed_time":0.09907548953,"remaining_time":12.2853607},
{"learn":[0.6364820089],"iteration":8,"passed_time":0.1145532488,"remaining_time":12.6135855},
{"learn":[0.6311550425],"iteration":9,"passed_time":0.1294024455,"remaining_time":12.8108421},
{"learn":[0.6264983184],"iteration":10,"passed_time":0.1413965551,"remaining_time":12.71283573},
{"learn":[0.6216464325],"iteration":11,"passed_time":0.1536412098,"remaining_time":12.64979294},
{"learn":[0.6170615777],"iteration":12,"passed_time":0.1668934445,"remaining_time":12.67106383},
{"learn":[0.6122169065],"iteration":13,"passed_time":0.1800224369,"remaining_time":12.67872305},
{"learn":[0.6076936832],"iteration":14,"passed_time":0.1958584333,"remaining_time":12.86137045},
{"learn":[0.603474186],"iteration":15,"passed_time":0.2109419549,"remaining_time":12.97293023},
{"learn":[0.5993346213],"iteration":16,"passed_time":0.2224851553,"remaining_time":12.86487692},
{"learn":[0.5950882715],"iteration":17,"passed_time":0.2344634849,"remaining_time":12.79128567},
{"learn":[0.5913968703],"iteration":18,"passed_time":0.2460709068,"remaining_time":12.70502945},
{"learn":[0.5873965101],"iteration":19,"passed_time":0.257591927,"remaining_time":12.62200442},
{"learn":[0.5839041162],"iteration":20,"passed_time":0.269305801,"remaining_time":12.55477996},
{"learn":[0.5806958271],"iteration":21,"passed_time":0.2824216231,"remaining_time":12.55492488},
{"learn":[0.5779175394],"iteration":22,"passed_time":0.2924189828,"remaining_time":12.42144984},
{"learn":[0.5745902065],"iteration":23,"passed_time":0.3059325342,"remaining_time":12.44125639},
{"learn":[0.5709249834],"iteration":24,"passed_time":0.3178706327,"remaining_time":12.39695468},
{"learn":[0.568015099],"iteration":25,"passed_time":0.3296922273,"remaining_time":12.35077805},
{"learn":[0.5645669236],"iteration":26,"passed_time":0.3423787724,"remaining_time":12.3383165},
{"learn":[0.5613594587],"iteration":27,"passed_time":0.3543018192,"remaining_time":12.29933458},
{"learn":[0.5586650686],"iteration":28,"passed_time":0.365803379,"remaining_time":12.24810624},
{"learn":[0.5555707801],"iteration":29,"passed_time":0.3777509878,"remaining_time":12.2139486},
{"learn":[0.5527098981],"iteration":30,"passed_time":0.389927171,"remaining_time":12.18836867},
{"learn":[0.5499762208],"iteration":31,"passed_time":0.4025184226,"remaining_time":12.17618228},
{"learn":[0.5472609875],"iteration":32,"passed_time":0.4155283123,"remaining_time":12.17623873},
{"learn":[0.5445622226],"iteration":33,"passed_time":0.42792639,"remaining_time":12.1581439},
{"learn":[0.5421035177],"iteration":34,"passed_time":0.4401588247,"remaining_time":12.13580759},
{"learn":[0.5397482278],"iteration":35,"passed_time":0.4528915791,"remaining_time":12.12743006},
{"learn":[0.5376309507],"iteration":36,"passed_time":0.466404519,"remaining_time":12.13912302},
{"learn":[0.5350905094],"iteration":37,"passed_time":0.4783415176,"remaining_time":12.10959315},
{"learn":[0.5331712022],"iteration":38,"passed_time":0.490141603,"remaining_time":12.07759181},
{"learn":[0.5303119831],"iteration":39,"passed_time":0.5021387827,"remaining_time":12.05133079},
{"learn":[0.5283959649],"iteration":40,"passed_time":0.5137453746,"remaining_time":12.01662962},
{"learn":[0.5267731773],"iteration":41,"passed_time":0.5257013535,"remaining_time":11.99099754},
{"learn":[0.5245311641],"iteration":42,"passed_time":0.5376928631,"remaining_time":11.96679233},
{"learn":[0.5217487802],"iteration":43,"passed_time":0.5497333937,"remaining_time":11.94420737},
{"learn":[0.5194342514],"iteration":44,"passed_time":0.5621346515,"remaining_time":11.92974649},
{"learn":[0.5173148885],"iteration":45,"passed_time":0.5739791281,"remaining_time":11.903828},
{"learn":[0.5157479517],"iteration":46,"passed_time":0.5859965182,"remaining_time":11.88201451},
{"learn":[0.5138905729],"iteration":47,"passed_time":0.5989151963,"remaining_time":11.87848473},
{"learn":[0.5125195063],"iteration":48,"passed_time":0.6076435507,"remaining_time":11.79324524},
{"learn":[0.5101647172],"iteration":49,"passed_time":0.6211666343,"remaining_time":11.80216605},
{"learn":[0.5082360318],"iteration":50,"passed_time":0.6403138738,"remaining_time":11.91486012},
{"learn":[0.5063513465],"iteration":51,"passed_time":0.6572912727,"remaining_time":11.98292551},
{"learn":[0.5051040857],"iteration":52,"passed_time":0.6699353053,"remaining_time":11.97035347},
{"learn":[0.5038271967],"iteration":53,"passed_time":0.6850909284,"remaining_time":12.00177812},
{"learn":[0.5018829435],"iteration":54,"passed_time":0.6981850298,"remaining_time":11.99608824},
{"learn":[0.500513679],"iteration":55,"passed_time":0.7136260383,"remaining_time":12.02969607},
{"learn":[0.4993029127],"iteration":56,"passed_time":0.7311465786,"remaining_time":12.09598638},
{"learn":[0.4978482811],"iteration":57,"passed_time":0.7436889292,"remaining_time":12.07853399},
{"learn":[0.4966717826],"iteration":58,"passed_time":0.7555260057,"remaining_time":12.04999951},
{"learn":[0.4953844754],"iteration":59,"passed_time":0.767504845,"remaining_time":12.02424257},
{"learn":[0.493862326],"iteration":60,"passed_time":0.779467124,"remaining_time":11.99868245},
{"learn":[0.4920393962],"iteration":61,"passed_time":0.7913322511,"remaining_time":11.97209115},
{"learn":[0.4907827807],"iteration":62,"passed_time":0.8036568474,"remaining_time":11.95280105},
{"learn":[0.4890137228],"iteration":63,"passed_time":0.8156259365,"remaining_time":11.92852932},
{"learn":[0.4875390321],"iteration":64,"passed_time":0.8278078299,"remaining_time":11.90769725},
{"learn":[0.4857134944],"iteration":65,"passed_time":0.8396786071,"remaining_time":11.88272453},
{"learn":[0.4841129948],"iteration":66,"passed_time":0.8516645466,"remaining_time":11.8597466},
{"learn":[0.4829102014],"iteration":67,"passed_time":0.8634774726,"remaining_time":11.83472065},
{"learn":[0.481993252],"iteration":68,"passed_time":0.8751947767,"remaining_time":11.80878749},
{"learn":[0.480954808],"iteration":69,"passed_time":0.887124515,"remaining_time":11.78608284},
{"learn":[0.4795969723],"iteration":70,"passed_time":0.8990241128,"remaining_time":11.76328734},
{"learn":[0.4782869801],"iteration":71,"passed_time":0.9112208562,"remaining_time":11.74462437},
{"learn":[0.4771661791],"iteration":72,"passed_time":0.9232619468,"remaining_time":11.72416198},
{"learn":[0.4758991169],"iteration":73,"passed_time":0.9359290515,"remaining_time":11.71176083},
{"learn":[0.474884222],"iteration":74,"passed_time":0.9479545618,"remaining_time":11.6914396},
{"learn":[0.4741380154],"iteration":75,"passed_time":0.9596437554,"remaining_time":11.66724776},
{"learn":[0.4728890776],"iteration":76,"passed_time":0.9717166552,"remaining_time":11.64798017},
{"learn":[0.4718068232],"iteration":77,"passed_time":0.983719705,"remaining_time":11.62807138},
{"learn":[0.4707723702],"iteration":78,"passed_time":0.9968131766,"remaining_time":11.62107514},
{"learn":[0.4700967804],"iteration":79,"passed_time":1.008582612,"remaining_time":11.59870004},
{"learn":[0.4690807845],"iteration":80,"passed_time":1.020336307,"remaining_time":11.57640822},
{"learn":[0.4680848836],"iteration":81,"passed_time":1.03253009,"remaining_time":11.55930028},
{"learn":[0.4671462323],"iteration":82,"passed_time":1.045164843,"remaining_time":11.54718266},
{"learn":[0.4660007221],"iteration":83,"passed_time":1.05754857,"remaining_time":11.53231536},
{"learn":[0.4649148751],"iteration":84,"passed_time":1.069347286,"remaining_time":11.51120902},
{"learn":[0.4637086247],"iteration":85,"passed_time":1.081265964,"remaining_time":11.49159408},
{"learn":[0.4628832667],"iteration":86,"passed_time":1.093000318,"remaining_time":11.47022173},
{"learn":[0.4623198997],"iteration":87,"passed_time":1.104660731,"remaining_time":11.44830212},
{"learn":[0.461254451],"iteration":88,"passed_time":1.118219212,"remaining_time":11.4460416},
{"learn":[0.4601153404],"iteration":89,"passed_time":1.130337824,"remaining_time":11.42897133},
{"learn":[0.4589812788],"iteration":90,"passed_time":1.142510817,"remaining_time":11.41255311},
{"learn":[0.4581554655],"iteration":91,"passed_time":1.155977827,"remaining_time":11.40899855},
{"learn":[0.4573546545],"iteration":92,"passed_time":1.174746821,"remaining_time":11.45693943},
{"learn":[0.4563379314],"iteration":93,"passed_time":1.190121789,"remaining_time":11.47074831},
{"learn":[0.4554036605],"iteration":94,"passed_time":1.203059067,"remaining_time":11.46072059},
{"learn":[0.454688977],"iteration":95,"passed_time":1.215015396,"remaining_time":11.44139498},
{"learn":[0.4538075707],"iteration":96,"passed_time":1.227385413,"remaining_time":11.42607246},
{"learn":[0.4530080835],"iteration":97,"passed_time":1.242074997,"remaining_time":11.43215966},
{"learn":[0.4517073322],"iteration":98,"passed_time":1.258845762,"remaining_time":11.45676799},
{"learn":[0.450923355],"iteration":99,"passed_time":1.274284831,"remaining_time":11.46856347},
{"learn":[0.4505483415],"iteration":100,"passed_time":1.288043365,"remaining_time":11.46486124},
{"learn":[0.449353517],"iteration":101,"passed_time":1.301073756,"remaining_time":11.4545513},
{"learn":[0.4486579926],"iteration":102,"passed_time":1.312972233,"remaining_time":11.434331},
{"learn":[0.447787717],"iteration":103,"passed_time":1.325106796,"remaining_time":11.4163047},
{"learn":[0.4474064526],"iteration":104,"passed_time":1.33685579,"remaining_time":11.39510412},
{"learn":[0.4469246052],"iteration":105,"passed_time":1.348578125,"remaining_time":11.37385701},
{"learn":[0.4464315428],"iteration":106,"passed_time":1.360150196,"remaining_time":11.35153388},
{"learn":[0.4457997194],"iteration":107,"passed_time":1.371816939,"remaining_time":11.33019176},
{"learn":[0.4449779703],"iteration":108,"passed_time":1.38384858,"remaining_time":11.31200995},
{"learn":[0.4443572091],"iteration":109,"passed_time":1.395620795,"remaining_time":11.29184098},
{"learn":[0.4436183366],"iteration":110,"passed_time":1.407610624,"remaining_time":11.27356617},
{"learn":[0.442749142],"iteration":111,"passed_time":1.419496702,"remaining_time":11.25458099},
{"learn":[0.4417506427],"iteration":112,"passed_time":1.431540132,"remaining_time":11.23695662},
{"learn":[0.4413632699],"iteration":113,"passed_time":1.443331138,"remaining_time":11.21746832},
{"learn":[0.4407300876],"iteration":114,"passed_time":1.456313557,"remaining_time":11.20728259},
{"learn":[0.4400142805],"iteration":115,"passed_time":1.469755066,"remaining_time":11.20054723},
{"learn":[0.4390080163],"iteration":116,"passed_time":1.482537671,"remaining_time":11.18872448},
{"learn":[0.4383774706],"iteration":117,"passed_time":1.49497395,"remaining_time":11.17429681},
{"learn":[0.4377627005],"iteration":118,"passed_time":1.507664153,"remaining_time":11.16178251},
{"learn":[0.4368843089],"iteration":119,"passed_time":1.51998963,"remaining_time":11.14659062},
{"learn":[0.4361645546],"iteration":120,"passed_time":1.531827716,"remaining_time":11.12790548},
{"learn":[0.4351539469],"iteration":121,"passed_time":1.543905288,"remaining_time":11.11105609},
{"learn":[0.4343997468],"iteration":122,"passed_time":1.555683623,"remaining_time":11.09215071},
{"learn":[0.4339135119],"iteration":123,"passed_time":1.56739099,"remaining_time":11.07285893},
{"learn":[0.4333272427],"iteration":124,"passed_time":1.579850565,"remaining_time":11.05895396},
{"learn":[0.4325135299],"iteration":125,"passed_time":1.59159358,"remaining_time":11.0401015},
{"learn":[0.4318031753],"iteration":126,"passed_time":1.603535729,"remaining_time":11.02272985},
{"learn":[0.4312012097],"iteration":127,"passed_time":1.61609221,"remaining_time":11.00962818},
{"learn":[0.4306598992],"iteration":128,"passed_time":1.628517478,"remaining_time":10.99564902},
{"learn":[0.4293122087],"iteration":129,"passed_time":1.641999877,"remaining_time":10.98876841},
{"learn":[0.4285388301],"iteration":130,"passed_time":1.654344194,"remaining_time":10.97423744},
{"learn":[0.4279567095],"iteration":131,"passed_time":1.666773412,"remaining_time":10.96029789},
{"learn":[0.4269469894],"iteration":132,"passed_time":1.679093589,"remaining_time":10.94567024},
{"learn":[0.4266041576],"iteration":133,"passed_time":1.696404126,"remaining_time":10.96332816},
{"learn":[0.4258961183],"iteration":134,"passed_time":1.714520456,"remaining_time":10.98563107},
{"learn":[0.4250959907],"iteration":135,"passed_time":1.727614558,"remaining_time":10.97543366},
{"learn":[0.4245931906],"iteration":136,"passed_time":1.740150398,"remaining_time":10.96167733},
{"learn":[0.4238369287],"iteration":137,"passed_time":1.752313461,"remaining_time":10.94561017},
{"learn":[0.4233640611],"iteration":138,"passed_time":1.764523695,"remaining_time":10.92989138},
{"learn":[0.4227531123],"iteration":139,"passed_time":1.780633287,"remaining_time":10.93817591},
{"learn":[0.4221509572],"iteration":140,"passed_time":1.796658848,"remaining_time":10.94560248},
{"learn":[0.4218380585],"iteration":141,"passed_time":1.81032114,"remaining_time":10.93841928},
{"learn":[0.4213321959],"iteration":142,"passed_time":1.822352481,"remaining_time":10.92137116},
{"learn":[0.4206582354],"iteration":143,"passed_time":1.83433593,"remaining_time":10.90410803},
{"learn":[0.4204124485],"iteration":144,"passed_time":1.845963873,"remaining_time":10.88482146},
{"learn":[0.4197945666],"iteration":145,"passed_time":1.857540124,"remaining_time":10.86533744},
{"learn":[0.4193828127],"iteration":146,"passed_time":1.869122455,"remaining_time":10.84599629},
{"learn":[0.4189793359],"iteration":147,"passed_time":1.881456302,"remaining_time":10.83108628},
{"learn":[0.418630006],"iteration":148,"passed_time":1.893694596,"remaining_time":10.81566511},
{"learn":[0.4176362561],"iteration":149,"passed_time":1.90588169,"remaining_time":10.79999624},
{"learn":[0.4168004977],"iteration":150,"passed_time":1.91839051,"remaining_time":10.7861824},
{"learn":[0.4163334648],"iteration":151,"passed_time":1.930590074,"remaining_time":10.77066041},
{"learn":[0.4162737964],"iteration":152,"passed_time":1.942303478,"remaining_time":10.75249049},
{"learn":[0.4156584753],"iteration":153,"passed_time":1.954795197,"remaining_time":10.73868011},
{"learn":[0.4154222123],"iteration":154,"passed_time":1.966823547,"remaining_time":10.72236063},
{"learn":[0.4149412686],"iteration":155,"passed_time":1.978704175,"remaining_time":10.70529695},
{"learn":[0.4146798377],"iteration":156,"passed_time":1.990596302,"remaining_time":10.68836104},
{"learn":[0.4142037584],"iteration":157,"passed_time":2.002712535,"remaining_time":10.67268325},
{"learn":[0.4138005623],"iteration":158,"passed_time":2.014834188,"remaining_time":10.65707894},
{"learn":[0.413191154],"iteration":159,"passed_time":2.026522792,"remaining_time":10.63924466},
{"learn":[0.4127034375],"iteration":160,"passed_time":2.038721325,"remaining_time":10.62414405},
{"learn":[0.4121437992],"iteration":161,"passed_time":2.050872458,"remaining_time":10.60883407},
{"learn":[0.4118524983],"iteration":162,"passed_time":2.062674804,"remaining_time":10.59177185},
{"learn":[0.4112548028],"iteration":163,"passed_time":2.074648032,"remaining_time":10.57564484},
{"learn":[0.4105715885],"iteration":164,"passed_time":2.08655413,"remaining_time":10.55922847},
{"learn":[0.4098529137],"iteration":165,"passed_time":2.098344805,"remaining_time":10.54228655},
{"learn":[0.4092273533],"iteration":166,"passed_time":2.110319615,"remaining_time":10.52632478},
{"learn":[0.4087366153],"iteration":167,"passed_time":2.123150741,"remaining_time":10.51465129},
{"learn":[0.4084977567],"iteration":168,"passed_time":2.135297485,"remaining_time":10.49959888},
{"learn":[0.408142151],"iteration":169,"passed_time":2.147168462,"remaining_time":10.48323426},
{"learn":[0.4078217518],"iteration":170,"passed_time":2.158918546,"remaining_time":10.46633611},
{"learn":[0.4075212264],"iteration":171,"passed_time":2.171554218,"remaining_time":10.453761},
{"learn":[0.4068302321],"iteration":172,"passed_time":2.184394836,"remaining_time":10.44216491},
{"learn":[0.4066109722],"iteration":173,"passed_time":2.199506606,"remaining_time":10.44133596},
{"learn":[0.4063601278],"iteration":174,"passed_time":2.220548207,"remaining_time":10.46829869},
{"learn":[0.4060050401],"iteration":175,"passed_time":2.234791971,"remaining_time":10.46288968},
{"learn":[0.4054696462],"iteration":176,"passed_time":2.247319802,"remaining_time":10.44940224},
{"learn":[0.4050986396],"iteration":177,"passed_time":2.260017545,"remaining_time":10.43671024},
{"learn":[0.4049662131],"iteration":178,"passed_time":2.272677138,"remaining_time":10.42384319},
{"learn":[0.4041173434],"iteration":179,"passed_time":2.288864422,"remaining_time":10.42704903},
{"learn":[0.4036907783],"iteration":180,"passed_time":2.308259839,"remaining_time":10.44455695},
{"learn":[0.4032877362],"iteration":181,"passed_time":2.320423052,"remaining_time":10.42915416},
{"learn":[0.4029992932],"iteration":182,"passed_time":2.332480363,"remaining_time":10.41331397},
{"learn":[0.4024666745],"iteration":183,"passed_time":2.344910151,"remaining_time":10.39916676},
{"learn":[0.4018874053],"iteration":184,"passed_time":2.356984224,"remaining_time":10.38347104},
{"learn":[0.4013095728],"iteration":185,"passed_time":2.368885531,"remaining_time":10.36705818},
{"learn":[0.4008990182],"iteration":186,"passed_time":2.380952871,"remaining_time":10.35141543},
{"learn":[0.4007222985],"iteration":187,"passed_time":2.392771238,"remaining_time":10.33473535},
{"learn":[0.4004702403],"iteration":188,"passed_time":2.404728557,"remaining_time":10.31870296},
{"learn":[0.3999299839],"iteration":189,"passed_time":2.417198566,"remaining_time":10.30489915},
{"learn":[0.3997947475],"iteration":190,"passed_time":2.429117574,"remaining_time":10.28877548},
{"learn":[0.3994183927],"iteration":191,"passed_time":2.441268917,"remaining_time":10.27367336},
{"learn":[0.3990042852],"iteration":192,"passed_time":2.453424529,"remaining_time":10.25861966},
{"learn":[0.3984357656],"iteration":193,"passed_time":2.465517811,"remaining_time":10.24333689},
{"learn":[0.3981050851],"iteration":194,"passed_time":2.477531401,"remaining_time":10.22775784},
{"learn":[0.397793409],"iteration":195,"passed_time":2.489644703,"remaining_time":10.21262419},
{"learn":[0.3969874191],"iteration":196,"passed_time":2.501802466,"remaining_time":10.19770244},
{"learn":[0.3965826548],"iteration":197,"passed_time":2.514315186,"remaining_time":10.18424636},
{"learn":[0.3961163301],"iteration":198,"passed_time":2.52652233,"remaining_time":10.16956978},
{"learn":[0.3959604499],"iteration":199,"passed_time":2.53851945,"remaining_time":10.1540778},
{"learn":[0.3955858211],"iteration":200,"passed_time":2.551108711,"remaining_time":10.14097443},
{"learn":[0.3952685264],"iteration":201,"passed_time":2.564229104,"remaining_time":10.12997438},
{"learn":[0.394565135],"iteration":202,"passed_time":2.576847776,"remaining_time":10.11698363},
{"learn":[0.394323379],"iteration":203,"passed_time":2.588759063,"remaining_time":10.10123635},
{"learn":[0.3936210476],"iteration":204,"passed_time":2.600760583,"remaining_time":10.08587641},
{"learn":[0.39327395],"iteration":205,"passed_time":2.61309408,"remaining_time":10.07182864},
{"learn":[0.3930746717],"iteration":206,"passed_time":2.625492339,"remaining_time":10.05804553},
{"learn":[0.3927206237],"iteration":207,"passed_time":2.638750873,"remaining_time":10.0475514},
{"learn":[0.3922841287],"iteration":208,"passed_time":2.651790383,"remaining_time":10.03620188},
{"learn":[0.3916206665],"iteration":209,"passed_time":2.664675791,"remaining_time":10.02425655},
{"learn":[0.3908396198],"iteration":210,"passed_time":2.677626369,"remaining_time":10.012546},
{"learn":[0.3906167165],"iteration":211,"passed_time":2.692362613,"remaining_time":10.00746103},
{"learn":[0.3901504903],"iteration":212,"passed_time":2.70806221,"remaining_time":10.00584488},
{"learn":[0.3899940368],"iteration":213,"passed_time":2.720402294,"remaining_time":9.991757958},
{"learn":[0.3896518599],"iteration":214,"passed_time":2.73323905,"remaining_time":9.979500718},
{"learn":[0.388884274],"iteration":215,"passed_time":2.748124618,"remaining_time":9.974674538},
{"learn":[0.3887476723],"iteration":216,"passed_time":2.768573006,"remaining_time":9.989827944},
{"learn":[0.388577824],"iteration":217,"passed_time":2.781787942,"remaining_time":9.978707204},
{"learn":[0.3884260118],"iteration":218,"passed_time":2.793766931,"remaining_time":9.963159695},
{"learn":[0.3879156339],"iteration":219,"passed_time":2.805979815,"remaining_time":9.94847389},
{"learn":[0.3876985935],"iteration":220,"passed_time":2.818770539,"remaining_time":9.935847286},
{"learn":[0.3873463306],"iteration":221,"passed_time":2.83534302,"remaining_time":9.936472387},
{"learn":[0.3872507998],"iteration":222,"passed_time":2.853368421,"remaining_time":9.942005663},
{"learn":[0.3869048041],"iteration":223,"passed_time":2.865648926,"remaining_time":9.927426637},
{"learn":[0.3866689181],"iteration":224,"passed_time":2.877637705,"remaining_time":9.911863207},
{"learn":[0.3863364169],"iteration":225,"passed_time":2.889609904,"remaining_time":9.896274629},
{"learn":[0.3860396538],"iteration":226,"passed_time":2.9014101,"remaining_time":9.880132192},
{"learn":[0.3855404115],"iteration":227,"passed_time":2.913499432,"remaining_time":9.865006848},
{"learn":[0.3851886222],"iteration":228,"passed_time":2.92542195,"remaining_time":9.849346392},
{"learn":[0.3845798436],"iteration":229,"passed_time":2.937541792,"remaining_time":9.834379044},
{"learn":[0.3842004064],"iteration":230,"passed_time":2.950132844,"remaining_time":9.821005009},
{"learn":[0.3835532089],"iteration":231,"passed_time":2.962767358,"remaining_time":9.807781598},
{"learn":[0.3833442026],"iteration":232,"passed_time":2.974618225,"remaining_time":9.791983598},
{"learn":[0.3831696815],"iteration":233,"passed_time":2.986420949,"remaining_time":9.776061738},
{"learn":[0.3829318236],"iteration":234,"passed_time":2.998573242,"remaining_time":9.761312893},
{"learn":[0.3825921864],"iteration":235,"passed_time":3.010576791,"remaining_time":9.746104528},
{"learn":[0.3825501507],"iteration":236,"passed_time":3.022132192,"remaining_time":9.729480433},
{"learn":[0.3823586797],"iteration":237,"passed_time":3.034077131,"remaining_time":9.714146109},
{"learn":[0.3819621618],"iteration":238,"passed_time":3.046666283,"remaining_time":9.700891386},
{"learn":[0.3817899396],"iteration":239,"passed_time":3.058598651,"remaining_time":9.685562394},
{"learn":[0.3816090296],"iteration":240,"passed_time":3.070849916,"remaining_time":9.671265917},
{"learn":[0.38106255],"iteration":241,"passed_time":3.083481378,"remaining_time":9.65817721},
{"learn":[0.3806334574],"iteration":242,"passed_time":3.095426217,"remaining_time":9.642953277},
{"learn":[0.3803932093],"iteration":243,"passed_time":3.107504,"remaining_time":9.62816813},
{"learn":[0.3800214601],"iteration":244,"passed_time":3.119385427,"remaining_time":9.612799989},
{"learn":[0.3799280551],"iteration":245,"passed_time":3.130929288,"remaining_time":9.59642554},
{"learn":[0.3796414597],"iteration":246,"passed_time":3.143047768,"remaining_time":9.581841981},
{"learn":[0.3790315205],"iteration":247,"passed_time":3.155466437,"remaining_time":9.56818855},
{"learn":[0.3786624107],"iteration":248,"passed_time":3.167873954,"remaining_time":9.554511405},
{"learn":[0.3783028466],"iteration":249,"passed_time":3.179730661,"remaining_time":9.539191984},
{"learn":[0.3778638232],"iteration":250,"passed_time":3.191896184,"remaining_time":9.524821682},
{"learn":[0.3776269246],"iteration":251,"passed_time":3.203755963,"remaining_time":9.50956135},
{"learn":[0.3773751468],"iteration":252,"passed_time":3.216246981,"remaining_time":9.496191679},
{"learn":[0.3771677509],"iteration":253,"passed_time":3.228958996,"remaining_time":9.483477997},
{"learn":[0.3770159203],"iteration":254,"passed_time":3.240938646,"remaining_time":9.468624671},
{"learn":[0.3768760586],"iteration":255,"passed_time":3.253119788,"remaining_time":9.454379383},
{"learn":[0.3765461931],"iteration":256,"passed_time":3.269708979,"remaining_time":9.452894052},
{"learn":[0.3762647415],"iteration":257,"passed_time":3.286394572,"remaining_time":9.451568886},
{"learn":[0.3759184783],"iteration":258,"passed_time":3.30131895,"remaining_time":9.445086264},
{"learn":[0.3754827015],"iteration":259,"passed_time":3.317126597,"remaining_time":9.441052621},
{"learn":[0.3751052458],"iteration":260,"passed_time":3.329912123,"remaining_time":9.428371874},
{"learn":[0.3747155773],"iteration":261,"passed_time":3.346220898,"remaining_time":9.425614589},
{"learn":[0.3742808974],"iteration":262,"passed_time":3.364934663,"remaining_time":9.429493714},
{"learn":[0.374158577],"iteration":263,"passed_time":3.378226887,"remaining_time":9.418087079},
{"learn":[0.3740062637],"iteration":264,"passed_time":3.390078184,"remaining_time":9.40266968},
{"learn":[0.3736103862],"iteration":265,"passed_time":3.402011272,"remaining_time":9.387504789},
{"learn":[0.3729724863],"iteration":266,"passed_time":3.413873109,"remaining_time":9.372168498},
{"learn":[0.3724739215],"iteration":267,"passed_time":3.42590386,"remaining_time":9.357319497},
{"learn":[0.3719478213],"iteration":268,"passed_time":3.438189375,"remaining_time":9.343183767},
{"learn":[0.3714632614],"iteration":269,"passed_time":3.450145244,"remaining_time":9.328170474},
{"learn":[0.3709491119],"iteration":270,"passed_time":3.462949923,"remaining_time":9.315463077},
{"learn":[0.3707644889],"iteration":271,"passed_time":3.474843307,"remaining_time":9.300315911},
{"learn":[0.3705963784],"iteration":272,"passed_time":3.486598312,"remaining_time":9.284824077},
{"learn":[0.3704867967],"iteration":273,"passed_time":3.498929899,"remaining_time":9.270887251},
{"learn":[0.370383332],"iteration":274,"passed_time":3.51100451,"remaining_time":9.256284618},
{"learn":[0.369955377],"iteration":275,"passed_time":3.523308986,"remaining_time":9.242303282},
{"learn":[0.3697292505],"iteration":276,"passed_time":3.535814186,"remaining_time":9.228857965},
{"learn":[0.3695725191],"iteration":277,"passed_time":3.547602591,"remaining_time":9.213557809},
{"learn":[0.3693352105],"iteration":278,"passed_time":3.559632802,"remaining_time":9.198907706},
{"learn":[0.3689974791],"iteration":279,"passed_time":3.57257099,"remaining_time":9.186611117},
{"learn":[0.3685668419],"iteration":280,"passed_time":3.585976768,"remaining_time":9.175506393},
{"learn":[0.3682317426],"iteration":281,"passed_time":3.599544079,"remaining_time":9.164796627},
{"learn":[0.3679779503],"iteration":282,"passed_time":3.612977388,"remaining_time":9.153727162},
{"learn":[0.3679450848],"iteration":283,"passed_time":3.626497068,"remaining_time":9.142858805},
{"learn":[0.3677941725],"iteration":284,"passed_time":3.639210922,"remaining_time":9.129950207},
{"learn":[0.3675227595],"iteration":285,"passed_time":3.651599449,"remaining_time":9.116230793},
{"learn":[0.3671535321],"iteration":286,"passed_time":3.664704651,"remaining_time":9.104301102},
{"learn":[0.3669234073],"iteration":287,"passed_time":3.677499077,"remaining_time":9.09159494},
{"learn":[0.3668276246],"iteration":288,"passed_time":3.68919639,"remaining_time":9.076189044},
{"learn":[0.366639837],"iteration":289,"passed_time":3.70166493,"remaining_time":9.062696897},
{"learn":[0.3663407106],"iteration":290,"passed_time":3.714093268,"remaining_time":9.049113838},
{"learn":[0.3661318151],"iteration":291,"passed_time":3.727698929,"remaining_time":9.038393295},
{"learn":[0.3659665493],"iteration":292,"passed_time":3.739791851,"remaining_time":9.024002863},
{"learn":[0.3658571299],"iteration":293,"passed_time":3.752607559,"remaining_time":9.01136373},
{"learn":[0.3656734423],"iteration":294,"passed_time":3.764643429,"remaining_time":8.996859721},
{"learn":[0.3652926926],"iteration":295,"passed_time":3.777942354,"remaining_time":8.985376409},
{"learn":[0.3651152722],"iteration":296,"passed_time":3.792050556,"remaining_time":8.975796433},
{"learn":[0.3647146298],"iteration":297,"passed_time":3.809860541,"remaining_time":8.974906376},
{"learn":[0.3645104896],"iteration":298,"passed_time":3.822943313,"remaining_time":8.962820275},
{"learn":[0.3642826677],"iteration":299,"passed_time":3.835290029,"remaining_time":8.949010069},
{"learn":[0.364217738],"iteration":300,"passed_time":3.847169397,"remaining_time":8.93412428},
{"learn":[0.3640743136],"iteration":301,"passed_time":3.859786839,"remaining_time":8.920964283},
{"learn":[0.3635165813],"iteration":302,"passed_time":3.874464592,"remaining_time":8.912547263},
{"learn":[0.3631190381],"iteration":303,"passed_time":3.891756628,"remaining_time":8.910074384},
{"learn":[0.3627035569],"iteration":304,"passed_time":3.904434481,"remaining_time":8.896990046},
{"learn":[0.3626428217],"iteration":305,"passed_time":3.91593141,"remaining_time":8.881230061},
{"learn":[0.3623403157],"iteration":306,"passed_time":3.927797371,"remaining_time":8.866330873},
{"learn":[0.3619720903],"iteration":307,"passed_time":3.940069094,"remaining_time":8.85236303},
{"learn":[0.3615059702],"iteration":308,"passed_time":3.952070444,"remaining_time":8.837801543},
{"learn":[0.3610906108],"iteration":309,"passed_time":3.964302949,"remaining_time":8.823771079},
{"learn":[0.3608748116],"iteration":310,"passed_time":3.97699503,"remaining_time":8.810770341},
{"learn":[0.3608181246],"iteration":311,"passed_time":3.986393208,"remaining_time":8.7905081},
{"learn":[0.3606820289],"iteration":312,"passed_time":3.998140773,"remaining_time":8.775471921},
{"learn":[0.3603094537],"iteration":313,"passed_time":4.009924709,"remaining_time":8.760536147},
{"learn":[0.3601989303],"iteration":314,"passed_time":4.021630663,"remaining_time":8.745450806},
{"learn":[0.3599034325],"iteration":315,"passed_time":4.033893348,"remaining_time":8.73159193},
{"learn":[0.3597527884],"iteration":316,"passed_time":4.045603872,"remaining_time":8.716553452},
{"learn":[0.3593971128],"iteration":317,"passed_time":4.057678172,"remaining_time":8.702316081},
{"learn":[0.3592896905],"iteration":318,"passed_time":4.069904117,"remaining_time":8.688415999},
{"learn":[0.3590395352],"iteration":319,"passed_time":4.082302556,"remaining_time":8.674892932},
{"learn":[0.3586616067],"iteration":320,"passed_time":4.094296416,"remaining_time":8.660521079},
{"learn":[0.358284492],"iteration":321,"passed_time":4.106319335,"remaining_time":8.646225183},
{"learn":[0.3579836497],"iteration":322,"passed_time":4.118159201,"remaining_time":8.631559687},
{"learn":[0.3579056191],"iteration":323,"passed_time":4.129876835,"remaining_time":8.616656606},
{"learn":[0.3578611638],"iteration":324,"passed_time":4.141493847,"remaining_time":8.601564144},
{"learn":[0.3576964702],"iteration":325,"passed_time":4.153830105,"remaining_time":8.587980034},
{"learn":[0.3575989478],"iteration":326,"passed_time":4.165651801,"remaining_time":8.573344533},
{"learn":[0.3573982633],"iteration":327,"passed_time":4.177581,"remaining_time":8.558946439},
{"learn":[0.3570942606],"iteration":328,"passed_time":4.189716012,"remaining_time":8.544983113},
{"learn":[0.3565936251],"iteration":329,"passed_time":4.201967297,"remaining_time":8.531266936},
{"learn":[0.3562158474],"iteration":330,"passed_time":4.213755843,"remaining_time":8.516624347},
{"learn":[0.3560342016],"iteration":331,"passed_time":4.225801002,"remaining_time":8.502515268},
{"learn":[0.3557103827],"iteration":332,"passed_time":4.237558156,"remaining_time":8.487841713},
{"learn":[0.3554609611],"iteration":333,"passed_time":4.251004625,"remaining_time":8.476554133},
{"learn":[0.3550621741],"iteration":334,"passed_time":4.263586197,"remaining_time":8.463536779},
{"learn":[0.3546998616],"iteration":335,"passed_time":4.278847952,"remaining_time":8.455818571},
{"learn":[0.3545054757],"iteration":336,"passed_time":4.292595806,"remaining_time":8.44507721},
{"learn":[0.3542335758],"iteration":337,"passed_time":4.304944913,"remaining_time":8.431578499},
{"learn":[0.3539586125],"iteration":338,"passed_time":4.320421404,"remaining_time":8.424184507},
{"learn":[0.3538652412],"iteration":339,"passed_time":4.337103437,"remaining_time":8.419083143},
{"learn":[0.3537474452],"iteration":340,"passed_time":4.35078203,"remaining_time":8.408109554},
{"learn":[0.3530973231],"iteration":341,"passed_time":4.363553034,"remaining_time":8.395373966},
{"learn":[0.3529831849],"iteration":342,"passed_time":4.376132457,"remaining_time":8.382271207},
{"learn":[0.3528027918],"iteration":343,"passed_time":4.388633415,"remaining_time":8.369021861},
{"learn":[0.3525773219],"iteration":344,"passed_time":4.40289293,"remaining_time":8.359115563},
{"learn":[0.3523745821],"iteration":345,"passed_time":4.419166565,"remaining_time":8.352991138},
{"learn":[0.3521490778],"iteration":346,"passed_time":4.433242217,"remaining_time":8.342671952},
{"learn":[0.3519432159],"iteration":347,"passed_time":4.445094863,"remaining_time":8.328166238},
{"learn":[0.3517008162],"iteration":348,"passed_time":4.456994511,"remaining_time":8.3137634},
{"learn":[0.3513675907],"iteration":349,"passed_time":4.468799137,"remaining_time":8.299198397},
{"learn":[0.3509342571],"iteration":350,"passed_time":4.480792748,"remaining_time":8.284998557},
{"learn":[0.3506223666],"iteration":351,"passed_time":4.492745897,"remaining_time":8.270736765},
{"learn":[0.3504358108],"iteration":352,"passed_time":4.504500662,"remaining_time":8.256124442},
{"learn":[0.3497804217],"iteration":353,"passed_time":4.516886398,"remaining_time":8.242679698},
{"learn":[0.3496713406],"iteration":354,"passed_time":4.529350567,"remaining_time":8.229383424},
{"learn":[0.3493035545],"iteration":355,"passed_time":4.54150288,"remaining_time":8.215527681},
{"learn":[0.349003799],"iteration":356,"passed_time":4.553551782,"remaining_time":8.201495226},
{"learn":[0.3487356493],"iteration":357,"passed_time":4.565893148,"remaining_time":8.187998327},
{"learn":[0.3486650533],"iteration":358,"passed_time":4.577738053,"remaining_time":8.173621427},
{"learn":[0.3483576951],"iteration":359,"passed_time":4.589761404,"remaining_time":8.159575828},
{"learn":[0.3481636005],"iteration":360,"passed_time":4.602272854,"remaining_time":8.146405411},
{"learn":[0.3480087719],"iteration":361,"passed_time":4.614562219,"remaining_time":8.132847226},
{"learn":[0.347725537],"iteration":362,"passed_time":4.626919416,"remaining_time":8.119415063},
{"learn":[0.347479641],"iteration":363,"passed_time":4.63913089,"remaining_time":8.105734192},
{"learn":[0.3473837699],"iteration":364,"passed_time":4.651455666,"remaining_time":8.092258488},
{"learn":[0.3468923812],"iteration":365,"passed_time":4.663824344,"remaining_time":8.07886512},
{"learn":[0.3468033034],"iteration":366,"passed_time":4.67817495,"remaining_time":8.068895758},
{"learn":[0.3465705169],"iteration":367,"passed_time":4.691682462,"remaining_time":8.057454662},
{"learn":[0.3462982277],"iteration":368,"passed_time":4.703923025,"remaining_time":8.04383585},
{"learn":[0.3456070318],"iteration":369,"passed_time":4.717164629,"remaining_time":8.031928963},
{"learn":[0.3452589259],"iteration":370,"passed_time":4.73223774,"remaining_time":8.023120051},
{"learn":[0.3450944868],"iteration":371,"passed_time":4.744570177,"remaining_time":8.009650729},
{"learn":[0.3446499363],"iteration":372,"passed_time":4.756402443,"remaining_time":7.995346734},
{"learn":[0.3445338744],"iteration":373,"passed_time":4.768370232,"remaining_time":7.981282795},
{"learn":[0.3443140164],"iteration":374,"passed_time":4.780476274,"remaining_time":7.967460457},
{"learn":[0.3442764196],"iteration":375,"passed_time":4.792959893,"remaining_time":7.954273866},
{"learn":[0.344100712],"iteration":376,"passed_time":4.805507204,"remaining_time":7.941196255},
{"learn":[0.3438308333],"iteration":377,"passed_time":4.818340441,"remaining_time":7.928591942},
{"learn":[0.3434518013],"iteration":378,"passed_time":4.834206588,"remaining_time":7.920955913},
{"learn":[0.3434128576],"iteration":379,"passed_time":4.852878821,"remaining_time":7.917854918},
{"learn":[0.3430187281],"iteration":380,"passed_time":4.866002703,"remaining_time":7.905657935},
{"learn":[0.3426731058],"iteration":381,"passed_time":4.878498943,"remaining_time":7.892440698},
{"learn":[0.3421627634],"iteration":382,"passed_time":4.891694396,"remaining_time":7.880353636},
{"learn":[0.3419784291],"iteration":383,"passed_time":4.904141675,"remaining_time":7.867060603},
{"learn":[0.341719479],"iteration":384,"passed_time":4.918947391,"remaining_time":7.857539338},
{"learn":[0.3413348723],"iteration":385,"passed_time":4.936364859,"remaining_time":7.852145138},
{"learn":[0.3412185732],"iteration":386,"passed_time":4.949803327,"remaining_time":7.840386149},
{"learn":[0.3407479253],"iteration":387,"passed_time":4.962247407,"remaining_time":7.827050034},
{"learn":[0.3401980627],"iteration":388,"passed_time":4.974828019,"remaining_time":7.813932955},
{"learn":[0.3397800342],"iteration":389,"passed_time":4.986896529,"remaining_time":7.800017647},
{"learn":[0.3394165006],"iteration":390,"passed_time":4.99897176,"remaining_time":7.786122255},
{"learn":[0.3393626475],"iteration":391,"passed_time":5.010644003,"remaining_time":7.771611107},
{"learn":[0.3392710366],"iteration":392,"passed_time":5.022338307,"remaining_time":7.757148479},
{"learn":[0.3389702639],"iteration":393,"passed_time":5.034083313,"remaining_time":7.742777887},
{"learn":[0.3386510607],"iteration":394,"passed_time":5.046644082,"remaining_time":7.72967005},
{"learn":[0.3383877003],"iteration":395,"passed_time":5.058980559,"remaining_time":7.716222872},
{"learn":[0.3377237635],"iteration":396,"passed_time":5.071216753,"remaining_time":7.702628972},
{"learn":[0.3373919698],"iteration":397,"passed_time":5.083291164,"remaining_time":7.688797188},
{"learn":[0.3373554412],"iteration":398,"passed_time":5.094859345,"remaining_time":7.674211696},
{"learn":[0.337311577],"iteration":399,"passed_time":5.106389266,"remaining_time":7.659583899},
{"learn":[0.337011894],"iteration":400,"passed_time":5.118492028,"remaining_time":7.645827243},
{"learn":[0.3368862785],"iteration":401,"passed_time":5.130191541,"remaining_time":7.631478959},
{"learn":[0.3364064159],"iteration":402,"passed_time":5.142407695,"remaining_time":7.617909167},
{"learn":[0.3361992179],"iteration":403,"passed_time":5.154049268,"remaining_time":7.603498425},
{"learn":[0.3359642526],"iteration":404,"passed_time":5.165829533,"remaining_time":7.589305117},
{"learn":[0.3357915943],"iteration":405,"passed_time":5.177707682,"remaining_time":7.575266905},
{"learn":[0.335560425],"iteration":406,"passed_time":5.189636529,"remaining_time":7.561313174},
{"learn":[0.3352003814],"iteration":407,"passed_time":5.201346383,"remaining_time":7.547051615},
{"learn":[0.3350199451],"iteration":408,"passed_time":5.212953905,"remaining_time":7.532654665},
{"learn":[0.3347038848],"iteration":409,"passed_time":5.225072407,"remaining_time":7.519006635},
{"learn":[0.3342279185],"iteration":410,"passed_time":5.237496357,"remaining_time":7.505803782},
{"learn":[0.3338925282],"iteration":411,"passed_time":5.250783221,"remaining_time":7.493836247},
{"learn":[0.3337490943],"iteration":412,"passed_time":5.266017645,"remaining_time":7.484630406},
{"learn":[0.3336764158],"iteration":413,"passed_time":5.277562096,"remaining_time":7.470172436},
{"learn":[0.3334428016],"iteration":414,"passed_time":5.289521105,"remaining_time":7.456312883},
{"learn":[0.3331621644],"iteration":415,"passed_time":5.302314531,"remaining_time":7.44363386},
{"learn":[0.3330014271],"iteration":416,"passed_time":5.314283,"remaining_time":7.429800933},
{"learn":[0.3326922772],"iteration":417,"passed_time":5.326677797,"remaining_time":7.416570522},
{"learn":[0.3324128639],"iteration":418,"passed_time":5.339368371,"remaining_time":7.403754233},
{"learn":[0.3320243754],"iteration":419,"passed_time":5.352404781,"remaining_time":7.391416126},
{"learn":[0.3317445728],"iteration":420,"passed_time":5.367787188,"remaining_time":7.382301145},
{"learn":[0.3315945054],"iteration":421,"passed_time":5.386623125,"remaining_time":7.37788665},
{"learn":[0.3314693703],"iteration":422,"passed_time":5.398970672,"remaining_time":7.364553375},
{"learn":[0.3312105679],"iteration":423,"passed_time":5.411496082,"remaining_time":7.351466375},
{"learn":[0.3310684261],"iteration":424,"passed_time":5.423531322,"remaining_time":7.337718848},
{"learn":[0.3307994189],"iteration":425,"passed_time":5.43625862,"remaining_time":7.324911849},
{"learn":[0.3303431254],"iteration":426,"passed_time":5.455011922,"remaining_time":7.320191642},
{"learn":[0.3298580584],"iteration":427,"passed_time":5.470622523,"remaining_time":7.311205802},
{"learn":[0.3294689479],"iteration":428,"passed_time":5.483216125,"remaining_time":7.298173443},
{"learn":[0.3291960846],"iteration":429,"passed_time":5.495351298,"remaining_time":7.284535441},
{"learn":[0.3290628554],"iteration":430,"passed_time":5.50698512,"remaining_time":7.270242537},
{"learn":[0.3287787444],"iteration":431,"passed_time":5.518853767,"remaining_time":7.256270694},
{"learn":[0.3284625703],"iteration":432,"passed_time":5.530759295,"remaining_time":7.24235686},
{"learn":[0.3281356838],"iteration":433,"passed_time":5.542342166,"remaining_time":7.228031489},
{"learn":[0.3281065476],"iteration":434,"passed_time":5.553857896,"remaining_time":7.213631521},
{"learn":[0.3280447789],"iteration":435,"passed_time":5.565579711,"remaining_time":7.199511369},
{"learn":[0.3279353958],"iteration":436,"passed_time":5.577283085,"remaining_time":7.185378436},
{"learn":[0.327687481],"iteration":437,"passed_time":5.58906511,"remaining_time":7.171357515},
{"learn":[0.3274051477],"iteration":438,"passed_time":5.600940367,"remaining_time":7.157465936},
{"learn":[0.3268944764],"iteration":439,"passed_time":5.61452734,"remaining_time":7.145762069},
{"learn":[0.3266743141],"iteration":440,"passed_time":5.627854265,"remaining_time":7.133720032},
{"learn":[0.3260877205],"iteration":441,"passed_time":5.642591359,"remaining_time":7.12345244},
{"learn":[0.3258614031],"iteration":442,"passed_time":5.655026538,"remaining_time":7.110270387},
{"learn":[0.3256310069],"iteration":443,"passed_time":5.667113989,"remaining_time":7.096656257},
{"learn":[0.3255911863],"iteration":444,"passed_time":5.679072598,"remaining_time":7.082888297},
{"learn":[0.3253485347],"iteration":445,"passed_time":5.694021087,"remaining_time":7.072842337},
{"learn":[0.3249869755],"iteration":446,"passed_time":5.707583858,"remaining_time":7.06106012},
{"learn":[0.3246739522],"iteration":447,"passed_time":5.72171345,"remaining_time":7.049968358},
{"learn":[0.3241340319],"iteration":448,"passed_time":5.734374883,"remaining_time":7.037061382},
{"learn":[0.3238752991],"iteration":449,"passed_time":5.747639638,"remaining_time":7.024892891},
{"learn":[0.323802302],"iteration":450,"passed_time":5.761650098,"remaining_time":7.013627281},
{"learn":[0.3234276605],"iteration":451,"passed_time":5.774248821,"remaining_time":7.000637951},
{"learn":[0.3229803604],"iteration":452,"passed_time":5.786626839,"remaining_time":6.987383843},
{"learn":[0.3222586722],"iteration":453,"passed_time":5.799977274,"remaining_time":6.975303065},
{"learn":[0.3221899662],"iteration":454,"passed_time":5.81178414,"remaining_time":6.961367816},
{"learn":[0.3215050446],"iteration":455,"passed_time":5.823937863,"remaining_time":6.947855696},
{"learn":[0.3211961473],"iteration":456,"passed_time":5.835947523,"remaining_time":6.934178347},
{"learn":[0.3208365877],"iteration":457,"passed_time":5.848873721,"remaining_time":6.921592919},
{"learn":[0.320481367],"iteration":458,"passed_time":5.861316049,"remaining_time":6.908435692},
{"learn":[0.3201728047],"iteration":459,"passed_time":5.873814619,"remaining_time":6.895347596},
{"learn":[0.319935847],"iteration":460,"passed_time":5.887032233,"remaining_time":6.883102763},
{"learn":[0.3198167651],"iteration":461,"passed_time":5.903755507,"remaining_time":6.874936067},
{"learn":[0.3195952807],"iteration":462,"passed_time":5.919218096,"remaining_time":6.865270232},
{"learn":[0.3194920084],"iteration":463,"passed_time":5.93192242,"remaining_time":6.85239314},
{"learn":[0.3194537985],"iteration":464,"passed_time":5.944883529,"remaining_time":6.839812232},
{"learn":[0.319315822],"iteration":465,"passed_time":5.958410529,"remaining_time":6.82787816},
{"learn":[0.3191072121],"iteration":466,"passed_time":5.972612963,"remaining_time":6.816708157},
{"learn":[0.3190533619],"iteration":467,"passed_time":5.989191744,"remaining_time":6.808226513},
{"learn":[0.3187718577],"iteration":468,"passed_time":6.00396661,"remaining_time":6.797667953},
{"learn":[0.3184859284],"iteration":469,"passed_time":6.016774906,"remaining_time":6.78487383},
{"learn":[0.3181262089],"iteration":470,"passed_time":6.034212654,"remaining_time":6.77727918},
{"learn":[0.3177476371],"iteration":471,"passed_time":6.049834716,"remaining_time":6.767611716},
{"learn":[0.3177099221],"iteration":472,"passed_time":6.061420138,"remaining_time":6.753421591},
{"learn":[0.3172565403],"iteration":473,"passed_time":6.07356816,"remaining_time":6.739866777},
{"learn":[0.3171872071],"iteration":474,"passed_time":6.085215813,"remaining_time":6.725764846},
{"learn":[0.3170135057],"iteration":475,"passed_time":6.096960077,"remaining_time":6.711779581},
{"learn":[0.3167682359],"iteration":476,"passed_time":6.109317795,"remaining_time":6.698476324},
{"learn":[0.3165220502],"iteration":477,"passed_time":6.121748853,"remaining_time":6.685257116},
{"learn":[0.3159978],"iteration":478,"passed_time":6.134265093,"remaining_time":6.672133849},
{"learn":[0.3159648411],"iteration":479,"passed_time":6.145928796,"remaining_time":6.658089529},
{"learn":[0.3159152067],"iteration":480,"passed_time":6.157336124,"remaining_time":6.643778479},
{"learn":[0.3156391917],"iteration":481,"passed_time":6.169301053,"remaining_time":6.630078725},
{"learn":[0.3155843286],"iteration":482,"passed_time":6.180903425,"remaining_time":6.615998076},
{"learn":[0.3154879844],"iteration":483,"passed_time":6.192571208,"remaining_time":6.601997403},
{"learn":[0.3153059471],"iteration":484,"passed_time":6.204506786,"remaining_time":6.588290711},
{"learn":[0.3152767541],"iteration":485,"passed_time":6.216024918,"remaining_time":6.57414981},
{"learn":[0.3151502271],"iteration":486,"passed_time":6.228315472,"remaining_time":6.560833341},
{"learn":[0.3149481277],"iteration":487,"passed_time":6.240517036,"remaining_time":6.54742771},
{"learn":[0.3147312915],"iteration":488,"passed_time":6.255578728,"remaining_time":6.537015808},
{"learn":[0.3144513194],"iteration":489,"passed_time":6.268410753,"remaining_time":6.524264253},
{"learn":[0.3144144758],"iteration":490,"passed_time":6.280364962,"remaining_time":6.510602374},
{"learn":[0.3142831358],"iteration":491,"passed_time":6.292099447,"remaining_time":6.496720567},
{"learn":[0.3141163685],"iteration":492,"passed_time":6.303920833,"remaining_time":6.48293684},
{"learn":[0.3140740611],"iteration":493,"passed_time":6.315249659,"remaining_time":6.468656533},
{"learn":[0.3140396079],"iteration":494,"passed_time":6.32680466,"remaining_time":6.454618896},
{"learn":[0.3139952829],"iteration":495,"passed_time":6.338563865,"remaining_time":6.440798766},
{"learn":[0.3137413568],"iteration":496,"passed_time":6.350377321,"remaining_time":6.427041836},
{"learn":[0.3133830947],"iteration":497,"passed_time":6.362713007,"remaining_time":6.413819136},
{"learn":[0.313211722],"iteration":498,"passed_time":6.375104145,"remaining_time":6.400655665},
{"learn":[0.3128603147],"iteration":499,"passed_time":6.387278758,"remaining_time":6.387278758},
{"learn":[0.3128356989],"iteration":500,"passed_time":6.399025973,"remaining_time":6.373480959},
{"learn":[0.3128101801],"iteration":501,"passed_time":6.411266447,"remaining_time":6.360180659},
{"learn":[0.3126972401],"iteration":502,"passed_time":6.426480031,"remaining_time":6.349822218},
{"learn":[0.3126257164],"iteration":503,"passed_time":6.444143814,"remaining_time":6.341855817},
{"learn":[0.3120791159],"iteration":504,"passed_time":6.457171265,"remaining_time":6.329306487},
{"learn":[0.3118140266],"iteration":505,"passed_time":6.470024281,"remaining_time":6.31658497},
{"learn":[0.3116878412],"iteration":506,"passed_time":6.482383708,"remaining_time":6.303382975},
{"learn":[0.3116068759],"iteration":507,"passed_time":6.494588582,"remaining_time":6.290034611},
{"learn":[0.3115592701],"iteration":508,"passed_time":6.509121062,"remaining_time":6.278936035},
{"learn":[0.3111990182],"iteration":509,"passed_time":6.526412148,"remaining_time":6.270474417},
{"learn":[0.3106195714],"iteration":510,"passed_time":6.539233524,"remaining_time":6.257700965},
{"learn":[0.3104103336],"iteration":511,"passed_time":6.551212065,"remaining_time":6.244123999},
{"learn":[0.309957918],"iteration":512,"passed_time":6.563352796,"remaining_time":6.230707235},
{"learn":[0.3099355638],"iteration":513,"passed_time":6.575754644,"remaining_time":6.217542328},
{"learn":[0.3097216146],"iteration":514,"passed_time":6.58909804,"remaining_time":6.205267087},
{"learn":[0.3094035452],"iteration":515,"passed_time":6.601287094,"remaining_time":6.191904949},
{"learn":[0.3088667723],"iteration":516,"passed_time":6.613365475,"remaining_time":6.178443955},
{"learn":[0.3085655127],"iteration":517,"passed_time":6.625278553,"remaining_time":6.164834484},
{"learn":[0.3082413272],"iteration":518,"passed_time":6.63711102,"remaining_time":6.151156841},
{"learn":[0.3080803011],"iteration":519,"passed_time":6.649044678,"remaining_time":6.137579703},
{"learn":[0.3078420684],"iteration":520,"passed_time":6.661254802,"remaining_time":6.124263052},
{"learn":[0.3075140367],"iteration":521,"passed_time":6.673889894,"remaining_time":6.111339788},
{"learn":[0.307096044],"iteration":522,"passed_time":6.686388954,"remaining_time":6.098293559},
{"learn":[0.3066978565],"iteration":523,"passed_time":6.698520257,"remaining_time":6.084915348},
{"learn":[0.3064600548],"iteration":524,"passed_time":6.711026986,"remaining_time":6.071881559},
{"learn":[0.305839923],"iteration":525,"passed_time":6.724875253,"remaining_time":6.060058688},
{"learn":[0.3055182902],"iteration":526,"passed_time":6.739950665,"remaining_time":6.049329534},
{"learn":[0.3053497334],"iteration":527,"passed_time":6.752885383,"remaining_time":6.036670267},
{"learn":[0.30531367],"iteration":528,"passed_time":6.765493415,"remaining_time":6.023719089},
{"learn":[0.3052786706],"iteration":529,"passed_time":6.782315221,"remaining_time":6.014505951},
{"learn":[0.3050318616],"iteration":530,"passed_time":6.797189448,"remaining_time":6.003543976},
{"learn":[0.3046846403],"iteration":531,"passed_time":6.809394724,"remaining_time":5.990219418},
{"learn":[0.3042631909],"iteration":532,"passed_time":6.821658429,"remaining_time":5.976950255},
{"learn":[0.3039820685],"iteration":533,"passed_time":6.833764489,"remaining_time":5.963547288},
{"learn":[0.3037102681],"iteration":534,"passed_time":6.845596085,"remaining_time":5.949910616},
{"learn":[0.3031430792],"iteration":535,"passed_time":6.857902053,"remaining_time":5.936691329},
{"learn":[0.302822137],"iteration":536,"passed_time":6.869893541,"remaining_time":5.9232043},
{"learn":[0.3024785529],"iteration":537,"passed_time":6.882074844,"remaining_time":5.909885833},
{"learn":[0.3021843619],"iteration":538,"passed_time":6.894258119,"remaining_time":5.896573271},
{"learn":[0.3019368462],"iteration":539,"passed_time":6.907060935,"remaining_time":5.883792648},
{"learn":[0.3018883799],"iteration":540,"passed_time":6.919285957,"remaining_time":5.870521727},
{"learn":[0.3014630113],"iteration":541,"passed_time":6.931832428,"remaining_time":5.857526295},
{"learn":[0.3014337688],"iteration":542,"passed_time":6.944182085,"remaining_time":5.844366874},
{"learn":[0.3009826521],"iteration":543,"passed_time":6.962563002,"remaining_time":5.836266046},
{"learn":[0.3005717794],"iteration":544,"passed_time":6.979723175,"remaining_time":5.827108339},
{"learn":[0.3005069375],"iteration":545,"passed_time":6.99348099,"remaining_time":5.815092252},
{"learn":[0.3002468861],"iteration":546,"passed_time":7.005963559,"remaining_time":5.802013697},
{"learn":[0.2997908627],"iteration":547,"passed_time":7.018720084,"remaining_time":5.789163281},
{"learn":[0.2997481915],"iteration":548,"passed_time":7.032418808,"remaining_time":5.777087217},
{"learn":[0.2994537688],"iteration":549,"passed_time":7.049293065,"remaining_time":5.767603417},
{"learn":[0.2994249797],"iteration":550,"passed_time":7.063275494,"remaining_time":5.755736292},
{"learn":[0.299071374],"iteration":551,"passed_time":7.075311945,"remaining_time":5.742282158},
{"learn":[0.2989940097],"iteration":552,"passed_time":7.08708252,"remaining_time":5.72861824},
{"learn":[0.2989618437],"iteration":553,"passed_time":7.098461617,"remaining_time":5.714645995},
{"learn":[0.2985471614],"iteration":554,"passed_time":7.110782774,"remaining_time":5.70143844},
{"learn":[0.2983326587],"iteration":555,"passed_time":7.123534109,"remaining_time":5.688577598},
{"learn":[0.2975892442],"iteration":556,"passed_time":7.135956057,"remaining_time":5.675455176},
{"learn":[0.2970306239],"iteration":557,"passed_time":7.148223012,"remaining_time":5.662212493},
{"learn":[0.2969749221],"iteration":558,"passed_time":7.160081269,"remaining_time":5.648650876},
{"learn":[0.2967507713],"iteration":559,"passed_time":7.171904545,"remaining_time":5.635067857},
{"learn":[0.2967055425],"iteration":560,"passed_time":7.183407925,"remaining_time":5.621240783},
{"learn":[0.2961736574],"iteration":561,"passed_time":7.195481966,"remaining_time":5.607866728},
{"learn":[0.2959811744],"iteration":562,"passed_time":7.20717909,"remaining_time":5.594204729},
{"learn":[0.2955126874],"iteration":563,"passed_time":7.21968378,"remaining_time":5.581173986},
{"learn":[0.2954776734],"iteration":564,"passed_time":7.232599058,"remaining_time":5.568461221},
{"learn":[0.2954443787],"iteration":565,"passed_time":7.2462352,"remaining_time":5.556300489},
{"learn":[0.2954069739],"iteration":566,"passed_time":7.258488885,"remaining_time":5.543078813},
{"learn":[0.295372423],"iteration":567,"passed_time":7.27025134,"remaining_time":5.529486934},
{"learn":[0.2949829444],"iteration":568,"passed_time":7.282561146,"remaining_time":5.516316088},
{"learn":[0.2949552039],"iteration":569,"passed_time":7.294491474,"remaining_time":5.502861989},
{"learn":[0.2944932146],"iteration":570,"passed_time":7.307153947,"remaining_time":5.489963298},
{"learn":[0.2940992721],"iteration":571,"passed_time":7.319110366,"remaining_time":5.476537127},
{"learn":[0.2940420003],"iteration":572,"passed_time":7.330699078,"remaining_time":5.46284207},
{"learn":[0.2937641157],"iteration":573,"passed_time":7.342793939,"remaining_time":5.449529997},
{"learn":[0.2934513347],"iteration":574,"passed_time":7.354416822,"remaining_time":5.435873303},
{"learn":[0.2933962793],"iteration":575,"passed_time":7.365885251,"remaining_time":5.422109976},
{"learn":[0.2933621631],"iteration":576,"passed_time":7.377694958,"remaining_time":5.408604796},
{"learn":[0.293329133],"iteration":577,"passed_time":7.389248299,"remaining_time":5.394918308},
{"learn":[0.2926935635],"iteration":578,"passed_time":7.401915181,"remaining_time":5.382048862},
{"learn":[0.2926606043],"iteration":579,"passed_time":7.414096345,"remaining_time":5.368828388},
{"learn":[0.2920148389],"iteration":580,"passed_time":7.426642756,"remaining_time":5.355874896},
{"learn":[0.291756538],"iteration":581,"passed_time":7.439015212,"remaining_time":5.342797867},
{"learn":[0.2911904368],"iteration":582,"passed_time":7.451880939,"remaining_time":5.330076075},
{"learn":[0.2909102159],"iteration":583,"passed_time":7.466325527,"remaining_time":5.318478458},
{"learn":[0.2904131919],"iteration":584,"passed_time":7.483137613,"remaining_time":5.308550615},
{"learn":[0.2899727734],"iteration":585,"passed_time":7.496848257,"remaining_time":5.296408154},
{"learn":[0.2895813642],"iteration":586,"passed_time":7.510665125,"remaining_time":5.284335088},
{"learn":[0.2892812865],"iteration":587,"passed_time":7.523249265,"remaining_time":5.271392342},
{"learn":[0.2892490934],"iteration":588,"passed_time":7.535637912,"remaining_time":5.258314401},
{"learn":[0.2890542828],"iteration":589,"passed_time":7.550972309,"remaining_time":5.247285842},
{"learn":[0.2890234549],"iteration":590,"passed_time":7.565863356,"remaining_time":5.235935893},
{"learn":[0.2889951898],"iteration":591,"passed_time":7.578178232,"remaining_time":5.222798512},
{"learn":[0.288432556],"iteration":592,"passed_time":7.592280824,"remaining_time":5.210890886},
{"learn":[0.2882083206],"iteration":593,"passed_time":7.604396696,"remaining_time":5.197617944},
{"learn":[0.2881745034],"iteration":594,"passed_time":7.615868815,"remaining_time":5.183910706},
{"learn":[0.2881432227],"iteration":595,"passed_time":7.627289363,"remaining_time":5.170176011},
{"learn":[0.2881125079],"iteration":596,"passed_time":7.639378657,"remaining_time":5.1569005},
{"learn":[0.2880789859],"iteration":597,"passed_time":7.651046,"remaining_time":5.143345304},
{"learn":[0.2880465215],"iteration":598,"passed_time":7.662620031,"remaining_time":5.129733944},
{"learn":[0.2880172862],"iteration":599,"passed_time":7.674311055,"remaining_time":5.11620737},
{"learn":[0.287988607],"iteration":600,"passed_time":7.685678472,"remaining_time":5.102472064},
{"learn":[0.287506919],"iteration":601,"passed_time":7.697683812,"remaining_time":5.089166374},
{"learn":[0.2874761054],"iteration":602,"passed_time":7.709581799,"remaining_time":5.075794319},
{"learn":[0.287086755],"iteration":603,"passed_time":7.721794473,"remaining_time":5.062633463},
{"learn":[0.2866911056],"iteration":604,"passed_time":7.734510706,"remaining_time":5.04980451},
{"learn":[0.2866564246],"iteration":605,"passed_time":7.7467464,"remaining_time":5.036663501},
{"learn":[0.2864240336],"iteration":606,"passed_time":7.758716309,"remaining_time":5.023353393},
{"learn":[0.2860501538],"iteration":607,"passed_time":7.771144788,"remaining_time":5.01034335},
{"learn":[0.2860195964],"iteration":608,"passed_time":7.783345803,"remaining_time":4.997189177},
{"learn":[0.2859928168],"iteration":609,"passed_time":7.797706608,"remaining_time":4.985418979},
{"learn":[0.2857002665],"iteration":610,"passed_time":7.81076932,"remaining_time":4.972813855},
{"learn":[0.2853227914],"iteration":611,"passed_time":7.8238088,"remaining_time":4.960192507},
{"learn":[0.2850251998],"iteration":612,"passed_time":7.836113696,"remaining_time":4.947106036},
{"learn":[0.2846999422],"iteration":613,"passed_time":7.848626326,"remaining_time":4.934152707},
{"learn":[0.2842857229],"iteration":614,"passed_time":7.861499323,"remaining_time":4.921426406},
{"learn":[0.2839926184],"iteration":615,"passed_time":7.873558114,"remaining_time":4.908192071},
{"learn":[0.2839657334],"iteration":616,"passed_time":7.885163156,"remaining_time":4.894679885},
{"learn":[0.2838108033],"iteration":617,"passed_time":7.896973182,"remaining_time":4.881300575},
{"learn":[0.283244104],"iteration":618,"passed_time":7.909588664,"remaining_time":4.868422102},
{"learn":[0.2832111605],"iteration":619,"passed_time":7.921093104,"remaining_time":4.854863515},
{"learn":[0.2828595155],"iteration":620,"passed_time":7.932979601,"remaining_time":4.841544716},
{"learn":[0.2825911084],"iteration":621,"passed_time":7.945230936,"remaining_time":4.828452241},
{"learn":[0.2825654336],"iteration":622,"passed_time":7.957307427,"remaining_time":4.815256662},
{"learn":[0.2825386892],"iteration":623,"passed_time":7.969671144,"remaining_time":4.802237741},
{"learn":[0.2825116636],"iteration":624,"passed_time":7.982422839,"remaining_time":4.789453704},
{"learn":[0.2820891901],"iteration":625,"passed_time":8.002110122,"remaining_time":4.780813396},
{"learn":[0.2818229285],"iteration":626,"passed_time":8.017601972,"remaining_time":4.769642002},
{"learn":[0.2812857326],"iteration":627,"passed_time":8.030518402,"remaining_time":4.756931282},
{"learn":[0.2810496426],"iteration":628,"passed_time":8.043878157,"remaining_time":4.744481393},
{"learn":[0.2808071035],"iteration":629,"passed_time":8.055864526,"remaining_time":4.731222023},
{"learn":[0.280510219],"iteration":630,"passed_time":8.068722093,"remaining_time":4.718476153},
{"learn":[0.2802532304],"iteration":631,"passed_time":8.086235955,"remaining_time":4.708441189},
{"learn":[0.2799842453],"iteration":632,"passed_time":8.102231514,"remaining_time":4.697502316},
{"learn":[0.2796490279],"iteration":633,"passed_time":8.114578309,"remaining_time":4.684441106},
{"learn":[0.2795634262],"iteration":634,"passed_time":8.126468777,"remaining_time":4.671119848},
{"learn":[0.2793477147],"iteration":635,"passed_time":8.138248942,"remaining_time":4.657739961},
{"learn":[0.2791608903],"iteration":636,"passed_time":8.150028628,"remaining_time":4.644364823},
{"learn":[0.278936879],"iteration":637,"passed_time":8.162039388,"remaining_time":4.631125797},
{"learn":[0.2786470554],"iteration":638,"passed_time":8.173872264,"remaining_time":4.617790121},
{"learn":[0.2786005479],"iteration":639,"passed_time":8.185888864,"remaining_time":4.604562486},
{"learn":[0.2783114629],"iteration":640,"passed_time":8.198351063,"remaining_time":4.591588193},
{"learn":[0.2777619065],"iteration":641,"passed_time":8.210934065,"remaining_time":4.578682859},
{"learn":[0.2773337062],"iteration":642,"passed_time":8.223681,"remaining_time":4.565869544},
{"learn":[0.277007649],"iteration":643,"passed_time":8.239262871,"remaining_time":4.554623575},
{"learn":[0.2767704737],"iteration":644,"passed_time":8.251826262,"remaining_time":4.541702826},
{"learn":[0.276491803],"iteration":645,"passed_time":8.263904163,"remaining_time":4.528517142},
{"learn":[0.2764681164],"iteration":646,"passed_time":8.275430023,"remaining_time":4.515033691},
{"learn":[0.2760380899],"iteration":647,"passed_time":8.287671178,"remaining_time":4.501944837},
{"learn":[0.2758248364],"iteration":648,"passed_time":8.299855421,"remaining_time":4.488827816},
{"learn":[0.2757982421],"iteration":649,"passed_time":8.311952243,"remaining_time":4.475666592},
{"learn":[0.2755711121],"iteration":650,"passed_time":8.324276689,"remaining_time":4.462630667},
{"learn":[0.2755396183],"iteration":651,"passed_time":8.335752439,"remaining_time":4.44914394},
{"learn":[0.2751963315],"iteration":652,"passed_time":8.347397911,"remaining_time":4.435753561},
{"learn":[0.2751694148],"iteration":653,"passed_time":8.35886851,"remaining_time":4.422276001},
{"learn":[0.2748588442],"iteration":654,"passed_time":8.371430961,"remaining_time":4.409379667},
{"learn":[0.2748303505],"iteration":655,"passed_time":8.383836009,"remaining_time":4.39640181},
{"learn":[0.2745553253],"iteration":656,"passed_time":8.396246037,"remaining_time":4.383428296},
{"learn":[0.2745295633],"iteration":657,"passed_time":8.409046163,"remaining_time":4.370659252},
{"learn":[0.27450353],"iteration":658,"passed_time":8.421097024,"remaining_time":4.357502405},
{"learn":[0.2743349559],"iteration":659,"passed_time":8.433187445,"remaining_time":4.34436929},
{"learn":[0.2739054486],"iteration":660,"passed_time":8.445544422,"remaining_time":4.331376035},
{"learn":[0.2735923676],"iteration":661,"passed_time":8.457850738,"remaining_time":4.318358836},
{"learn":[0.2735611337],"iteration":662,"passed_time":8.470490211,"remaining_time":4.305513124},
{"learn":[0.2733009516],"iteration":663,"passed_time":8.48395588,"remaining_time":4.293086108},
{"learn":[0.2732801463],"iteration":664,"passed_time":8.496854327,"remaining_time":4.280370225},
{"learn":[0.273253718],"iteration":665,"passed_time":8.510171854,"remaining_time":4.267863963},
{"learn":[0.2731959345],"iteration":666,"passed_time":8.527127312,"remaining_time":4.257171507},
{"learn":[0.2729132365],"iteration":667,"passed_time":8.544805596,"remaining_time":4.246819548},
{"learn":[0.2726110198],"iteration":668,"passed_time":8.559140002,"remaining_time":4.234791242},
{"learn":[0.2725794685],"iteration":669,"passed_time":8.571404747,"remaining_time":4.221736666},
{"learn":[0.2721802656],"iteration":670,"passed_time":8.586128271,"remaining_time":4.209890017},
{"learn":[0.2721557289],"iteration":671,"passed_time":8.599013318,"remaining_time":4.197137453},
{"learn":[0.2721363963],"iteration":672,"passed_time":8.618332144,"remaining_time":4.187510566},
{"learn":[0.2717534838],"iteration":673,"passed_time":8.63413377,"remaining_time":4.176153723},
{"learn":[0.2717293894],"iteration":674,"passed_time":8.646370075,"remaining_time":4.163067073},
{"learn":[0.2716880058],"iteration":675,"passed_time":8.658620969,"remaining_time":4.149989932},
{"learn":[0.2715030878],"iteration":676,"passed_time":8.671352174,"remaining_time":4.13714439},
{"learn":[0.2709943874],"iteration":677,"passed_time":8.684007617,"remaining_time":4.124263204},
{"learn":[0.2706994047],"iteration":678,"passed_time":8.696572178,"remaining_time":4.111339719},
{"learn":[0.2703909384],"iteration":679,"passed_time":8.708683781,"remaining_time":4.098204132},
{"learn":[0.270059903],"iteration":680,"passed_time":8.720820124,"remaining_time":4.085083142},
{"learn":[0.2700123715],"iteration":681,"passed_time":8.733175219,"remaining_time":4.072067038},
{"learn":[0.2699879716],"iteration":682,"passed_time":8.744894473,"remaining_time":4.058757757},
{"learn":[0.2696421249],"iteration":683,"passed_time":8.75772403,"remaining_time":4.045966072},
{"learn":[0.2695909482],"iteration":684,"passed_time":8.770926865,"remaining_time":4.033345931},
{"learn":[0.269567066],"iteration":685,"passed_time":8.782900854,"remaining_time":4.020161615},
{"learn":[0.2695432757],"iteration":686,"passed_time":8.794323942,"remaining_time":4.006729831},
{"learn":[0.2692458021],"iteration":687,"passed_time":8.806836452,"remaining_time":3.993797926},
{"learn":[0.2690314398],"iteration":688,"passed_time":8.821960503,"remaining_time":3.982046033},
{"learn":[0.2688245305],"iteration":689,"passed_time":8.834073587,"remaining_time":3.968931611},
{"learn":[0.2687510518],"iteration":690,"passed_time":8.846381021,"remaining_time":3.955906998},
{"learn":[0.2687247886],"iteration":691,"passed_time":8.859043024,"remaining_time":3.943042271},
{"learn":[0.2686854104],"iteration":692,"passed_time":8.871124075,"remaining_time":3.929920766},
{"learn":[0.2683569018],"iteration":693,"passed_time":8.883282348,"remaining_time":3.916836309},
{"learn":[0.2679170963],"iteration":694,"passed_time":8.895909131,"remaining_time":3.903960122},
{"learn":[0.2676537602],"iteration":695,"passed_time":8.908621146,"remaining_time":3.89112188},
{"learn":[0.2673832866],"iteration":696,"passed_time":8.921509602,"remaining_time":3.878360702},
{"learn":[0.2671361447],"iteration":697,"passed_time":8.933788257,"remaining_time":3.86533532},
{"learn":[0.2666907502],"iteration":698,"passed_time":8.945792087,"remaining_time":3.852193731},
{"learn":[0.2664393052],"iteration":699,"passed_time":8.957738206,"remaining_time":3.83903066},
{"learn":[0.2660037852],"iteration":700,"passed_time":8.971890899,"remaining_time":3.826812238},
{"learn":[0.265710995],"iteration":701,"passed_time":8.984302567,"remaining_time":3.813849238},
{"learn":[0.2653398599],"iteration":702,"passed_time":8.997394268,"remaining_time":3.801175103},
{"learn":[0.265159791],"iteration":703,"passed_time":9.009564321,"remaining_time":3.788112271},
{"learn":[0.2649411491],"iteration":704,"passed_time":9.02203433,"remaining_time":3.775177486},
{"learn":[0.2644213646],"iteration":705,"passed_time":9.034828936,"remaining_time":3.762379189},
{"learn":[0.2642582353],"iteration":706,"passed_time":9.047431758,"remaining_time":3.749501422},
{"learn":[0.2642004925],"iteration":707,"passed_time":9.061015879,"remaining_time":3.737029148},
{"learn":[0.2639679084],"iteration":708,"passed_time":9.077828985,"remaining_time":3.725879033},
{"learn":[0.2636301112],"iteration":709,"passed_time":9.091640821,"remaining_time":3.713487096},
{"learn":[0.2636101297],"iteration":710,"passed_time":9.103690852,"remaining_time":3.700375044},
{"learn":[0.2633341685],"iteration":711,"passed_time":9.116046469,"remaining_time":3.687389583},
{"learn":[0.262989901],"iteration":712,"passed_time":9.128499759,"remaining_time":3.674445205},
{"learn":[0.2625886252],"iteration":713,"passed_time":9.146046388,"remaining_time":3.663542391},
{"learn":[0.2621324289],"iteration":714,"passed_time":9.161708061,"remaining_time":3.651869647},
{"learn":[0.2621038546],"iteration":715,"passed_time":9.173302583,"remaining_time":3.638572533},
{"learn":[0.2617869572],"iteration":716,"passed_time":9.185427675,"remaining_time":3.625489585},
{"learn":[0.2615682385],"iteration":717,"passed_time":9.19719869,"remaining_time":3.612270238},
{"learn":[0.2613300907],"iteration":718,"passed_time":9.209154141,"remaining_time":3.599127001},
{"learn":[0.261095582],"iteration":719,"passed_time":9.221291303,"remaining_time":3.586057729},
{"learn":[0.2610733583],"iteration":720,"passed_time":9.234276161,"remaining_time":3.573319069},
{"learn":[0.260727281],"iteration":721,"passed_time":9.247779871,"remaining_time":3.560779507},
{"learn":[0.2604230422],"iteration":722,"passed_time":9.26026123,"remaining_time":3.547845589},
{"learn":[0.2601164153],"iteration":723,"passed_time":9.272715969,"remaining_time":3.534902773},
{"learn":[0.2597731769],"iteration":724,"passed_time":9.284531675,"remaining_time":3.521718911},
{"learn":[0.2595848133],"iteration":725,"passed_time":9.296463114,"remaining_time":3.508582497},
{"learn":[0.2595497484],"iteration":726,"passed_time":9.308224229,"remaining_time":3.495385439},
{"learn":[0.2595291806],"iteration":727,"passed_time":9.320452853,"remaining_time":3.482367},
{"learn":[0.2592898748],"iteration":728,"passed_time":9.332511774,"remaining_time":3.469287642},
{"learn":[0.259035846],"iteration":729,"passed_time":9.344434162,"remaining_time":3.456160581},
{"learn":[0.2587473857],"iteration":730,"passed_time":9.356646388,"remaining_time":3.443143472},
{"learn":[0.2587261024],"iteration":731,"passed_time":9.36832432,"remaining_time":3.429932948},
{"learn":[0.2583982936],"iteration":732,"passed_time":9.381008223,"remaining_time":3.417093036},
{"learn":[0.2582019061],"iteration":733,"passed_time":9.393077987,"remaining_time":3.404030987},
{"learn":[0.2579735595],"iteration":734,"passed_time":9.406019532,"remaining_time":3.391285954},
{"learn":[0.2577320831],"iteration":735,"passed_time":9.418083904,"remaining_time":3.378225748},
{"learn":[0.257540419],"iteration":736,"passed_time":9.42990574,"remaining_time":3.365081696},
{"learn":[0.2575146066],"iteration":737,"passed_time":9.441275177,"remaining_time":3.351780618},
{"learn":[0.2572489133],"iteration":738,"passed_time":9.453479431,"remaining_time":3.338779609},
{"learn":[0.2569843286],"iteration":739,"passed_time":9.465361848,"remaining_time":3.325667676},
{"learn":[0.2566234356],"iteration":740,"passed_time":9.477321039,"remaining_time":3.312585896},
{"learn":[0.2564108744],"iteration":741,"passed_time":9.489638145,"remaining_time":3.299631592},
{"learn":[0.2561619388],"iteration":742,"passed_time":9.501698066,"remaining_time":3.286590044},
{"learn":[0.2561415647],"iteration":743,"passed_time":9.513552241,"remaining_time":3.273480341},
{"learn":[0.2557836215],"iteration":744,"passed_time":9.526284336,"remaining_time":3.260674504},
{"learn":[0.2554511243],"iteration":745,"passed_time":9.539047071,"remaining_time":3.247879298},
{"learn":[0.2551299625],"iteration":746,"passed_time":9.551290845,"remaining_time":3.234908412},
{"learn":[0.2549111999],"iteration":747,"passed_time":9.563492249,"remaining_time":3.221925196},
{"learn":[0.2548929779],"iteration":748,"passed_time":9.579285354,"remaining_time":3.210147696},
{"learn":[0.254767969],"iteration":749,"passed_time":9.595491338,"remaining_time":3.198497113},
{"learn":[0.2544226414],"iteration":750,"passed_time":9.610192092,"remaining_time":3.186335327},
{"learn":[0.2540446844],"iteration":751,"passed_time":9.622909066,"remaining_time":3.173512564},
{"learn":[0.2538444117],"iteration":752,"passed_time":9.635293033,"remaining_time":3.160580849},
{"learn":[0.2534494524],"iteration":753,"passed_time":9.648525898,"remaining_time":3.147927548},
{"learn":[0.2533901035],"iteration":754,"passed_time":9.661386185,"remaining_time":3.135151808},
{"learn":[0.2533704475],"iteration":755,"passed_time":9.677083252,"remaining_time":3.12329142},
{"learn":[0.2531218625],"iteration":756,"passed_time":9.693572798,"remaining_time":3.111675284},
{"learn":[0.252894031],"iteration":757,"passed_time":9.705562828,"remaining_time":3.098609768},
{"learn":[0.2526305609],"iteration":758,"passed_time":9.717568227,"remaining_time":3.085551967},
{"learn":[0.252421971],"iteration":759,"passed_time":9.729557017,"remaining_time":3.07249169},
{"learn":[0.25226003],"iteration":760,"passed_time":9.741434694,"remaining_time":3.059399332},
{"learn":[0.2522415239],"iteration":761,"passed_time":9.752865323,"remaining_time":3.046170534},
{"learn":[0.2519392728],"iteration":762,"passed_time":9.764901683,"remaining_time":3.033134599},
{"learn":[0.2516424537],"iteration":763,"passed_time":9.777211119,"remaining_time":3.020185634},
{"learn":[0.2514054945],"iteration":764,"passed_time":9.790792402,"remaining_time":3.007629038},
{"learn":[0.251074979],"iteration":765,"passed_time":9.803173018,"remaining_time":2.994702985},
{"learn":[0.250622155],"iteration":766,"passed_time":9.815642917,"remaining_time":2.981805475},
{"learn":[0.2502886247],"iteration":767,"passed_time":9.830987133,"remaining_time":2.969777363},
{"learn":[0.2500546968],"iteration":768,"passed_time":9.843635576,"remaining_time":2.956930843},
{"learn":[0.2499907964],"iteration":769,"passed_time":9.855811039,"remaining_time":2.943943557},
{"learn":[0.2497875566],"iteration":770,"passed_time":9.867585415,"remaining_time":2.930839248},
{"learn":[0.2497684758],"iteration":771,"passed_time":9.879577126,"remaining_time":2.917802571},
{"learn":[0.249704889],"iteration":772,"passed_time":9.891855251,"remaining_time":2.904852706},
{"learn":[0.2494638889],"iteration":773,"passed_time":9.90429104,"remaining_time":2.891950614},
{"learn":[0.249445929],"iteration":774,"passed_time":9.916267587,"remaining_time":2.878916396},
{"learn":[0.2491296731],"iteration":775,"passed_time":9.929094974,"remaining_time":2.866130508},
{"learn":[0.2487757325],"iteration":776,"passed_time":9.942700186,"remaining_time":2.85356775},
{"learn":[0.2486030789],"iteration":777,"passed_time":9.955142524,"remaining_time":2.840670489},
{"learn":[0.2485846736],"iteration":778,"passed_time":9.968026682,"remaining_time":2.827899739},
{"learn":[0.2483056309],"iteration":779,"passed_time":9.980158384,"remaining_time":2.814916467},
{"learn":[0.2482691389],"iteration":780,"passed_time":9.991847818,"remaining_time":2.80181136},
{"learn":[0.2480810879],"iteration":781,"passed_time":10.00364604,"remaining_time":2.788740201},
{"learn":[0.2478992078],"iteration":782,"passed_time":10.01572112,"remaining_time":2.775749022},
{"learn":[0.2475804572],"iteration":783,"passed_time":10.0277705,"remaining_time":2.762753096},
{"learn":[0.2472273777],"iteration":784,"passed_time":10.03978074,"remaining_time":2.749748864},
{"learn":[0.2469984982],"iteration":785,"passed_time":10.05201639,"remaining_time":2.736808534},
{"learn":[0.2466649279],"iteration":786,"passed_time":10.06461603,"remaining_time":2.723968507},
{"learn":[0.2464779403],"iteration":787,"passed_time":10.07677256,"remaining_time":2.711009878},
{"learn":[0.2462762009],"iteration":788,"passed_time":10.08966816,"remaining_time":2.698250928},
{"learn":[0.2462564421],"iteration":789,"passed_time":10.10312063,"remaining_time":2.685639662},
{"learn":[0.2460573099],"iteration":790,"passed_time":10.11805396,"remaining_time":2.673417544},
{"learn":[0.2457242793],"iteration":791,"passed_time":10.13160205,"remaining_time":2.660824781},
{"learn":[0.2454632858],"iteration":792,"passed_time":10.14429736,"remaining_time":2.648007004},
{"learn":[0.2450215659],"iteration":793,"passed_time":10.15703996,"remaining_time":2.635201803},
{"learn":[0.2447863191],"iteration":794,"passed_time":10.16947992,"remaining_time":2.622318721},
{"learn":[0.2445759492],"iteration":795,"passed_time":10.18301698,"remaining_time":2.609717919},
{"learn":[0.2444111988],"iteration":796,"passed_time":10.19780788,"remaining_time":2.597434128},
{"learn":[0.2439754973],"iteration":797,"passed_time":10.21312322,"remaining_time":2.585276805},
{"learn":[0.2437688962],"iteration":798,"passed_time":10.22805987,"remaining_time":2.573016312},
{"learn":[0.2433578367],"iteration":799,"passed_time":10.24061273,"remaining_time":2.560153182},
{"learn":[0.243185011],"iteration":800,"passed_time":10.25253989,"remaining_time":2.547135377},
{"learn":[0.2431692635],"iteration":801,"passed_time":10.26422063,"remaining_time":2.534059457},
{"learn":[0.2427928825],"iteration":802,"passed_time":10.2763268,"remaining_time":2.521091382},
{"learn":[0.2426176089],"iteration":803,"passed_time":10.28831241,"remaining_time":2.50809606},
{"learn":[0.2423338021],"iteration":804,"passed_time":10.30025758,"remaining_time":2.495093451},
{"learn":[0.2420003515],"iteration":805,"passed_time":10.31254952,"remaining_time":2.482176933},
{"learn":[0.2415789609],"iteration":806,"passed_time":10.32488422,"remaining_time":2.469272187},
{"learn":[0.2413933158],"iteration":807,"passed_time":10.3368534,"remaining_time":2.456281996},
{"learn":[0.2411917728],"iteration":808,"passed_time":10.3494467,"remaining_time":2.443441681},
{"learn":[0.2408122202],"iteration":809,"passed_time":10.36213428,"remaining_time":2.430624089},
{"learn":[0.240427314],"iteration":810,"passed_time":10.37448382,"remaining_time":2.417728042},
{"learn":[0.2401286571],"iteration":811,"passed_time":10.38718011,"remaining_time":2.404913621},
{"learn":[0.2399148728],"iteration":812,"passed_time":10.39929346,"remaining_time":2.391965408},
{"learn":[0.2396100115],"iteration":813,"passed_time":10.41141246,"remaining_time":2.379020538},
{"learn":[0.239480328],"iteration":814,"passed_time":10.42311025,"remaining_time":2.365982082},
{"learn":[0.2392537408],"iteration":815,"passed_time":10.43487875,"remaining_time":2.352962855},
{"learn":[0.2390069068],"iteration":816,"passed_time":10.44715288,"remaining_time":2.340059948},
{"learn":[0.2389600844],"iteration":817,"passed_time":10.45878382,"remaining_time":2.32701547},
{"learn":[0.2388781436],"iteration":818,"passed_time":10.47101635,"remaining_time":2.314107399},
{"learn":[0.2386987765],"iteration":819,"passed_time":10.48301184,"remaining_time":2.301148941},
{"learn":[0.2386746917],"iteration":820,"passed_time":10.49438544,"remaining_time":2.288057239},
{"learn":[0.2386580247],"iteration":821,"passed_time":10.50585236,"remaining_time":2.274989927},
{"learn":[0.2382388048],"iteration":822,"passed_time":10.5183516,"remaining_time":2.262148521},
{"learn":[0.2380838264],"iteration":823,"passed_time":10.53205389,"remaining_time":2.249564909},
{"learn":[0.2378161072],"iteration":824,"passed_time":10.54473829,"remaining_time":2.236762667},
{"learn":[0.2375847724],"iteration":825,"passed_time":10.55695141,"remaining_time":2.223861435},
{"learn":[0.2375326194],"iteration":826,"passed_time":10.56857896,"remaining_time":2.210839371},
{"learn":[0.2372729538],"iteration":827,"passed_time":10.58130573,"remaining_time":2.198049017},
{"learn":[0.2370903251],"iteration":828,"passed_time":10.59409185,"remaining_time":2.185271057},
{"learn":[0.2368042197],"iteration":829,"passed_time":10.60663186,"remaining_time":2.17244267},
{"learn":[0.2365135644],"iteration":830,"passed_time":10.62062299,"remaining_time":2.159910091},
{"learn":[0.2364977853],"iteration":831,"passed_time":10.63883745,"remaining_time":2.148226794},
{"learn":[0.2362652918],"iteration":832,"passed_time":10.65469076,"remaining_time":2.13605445},
{"learn":[0.2360558873],"iteration":833,"passed_time":10.66749509,"remaining_time":2.123266408},
{"learn":[0.2358348348],"iteration":834,"passed_time":10.67943654,"remaining_time":2.110307818},
{"learn":[0.235816095],"iteration":835,"passed_time":10.69170075,"remaining_time":2.09741498},
{"learn":[0.2356398212],"iteration":836,"passed_time":10.70478569,"remaining_time":2.084683474},
{"learn":[0.2355014285],"iteration":837,"passed_time":10.721171,"remaining_time":2.072589143},
{"learn":[0.2351122935],"iteration":838,"passed_time":10.7375398,"remaining_time":2.060481415},
{"learn":[0.2350574709],"iteration":839,"passed_time":10.74926303,"remaining_time":2.047478672},
{"learn":[0.2349926806],"iteration":840,"passed_time":10.76109017,"remaining_time":2.034498617},
{"learn":[0.2349760627],"iteration":841,"passed_time":10.77263388,"remaining_time":2.021468115},
{"learn":[0.2349586123],"iteration":842,"passed_time":10.78417118,"remaining_time":2.008439947},
{"learn":[0.234911101],"iteration":843,"passed_time":10.79618771,"remaining_time":1.995503889},
{"learn":[0.234743385],"iteration":844,"passed_time":10.80934103,"remaining_time":1.982778532},
{"learn":[0.234677606],"iteration":845,"passed_time":10.8213123,"remaining_time":1.969836991},
{"learn":[0.2344706041],"iteration":846,"passed_time":10.83365074,"remaining_time":1.956964065},
{"learn":[0.2342886466],"iteration":847,"passed_time":10.84621818,"remaining_time":1.944133447},
{"learn":[0.234120793],"iteration":848,"passed_time":10.86145339,"remaining_time":1.93177793},
{"learn":[0.233939514],"iteration":849,"passed_time":10.87329057,"remaining_time":1.918815983},
{"learn":[0.2339237372],"iteration":850,"passed_time":10.88495856,"remaining_time":1.905827058},
{"learn":[0.2338683872],"iteration":851,"passed_time":10.89678654,"remaining_time":1.892869023},
{"learn":[0.2337386306],"iteration":852,"passed_time":10.90849126,"remaining_time":1.879892398},
{"learn":[0.2334943123],"iteration":853,"passed_time":10.92106021,"remaining_time":1.8670665},
{"learn":[0.2332876129],"iteration":854,"passed_time":10.93354618,"remaining_time":1.85422713},
{"learn":[0.233225967],"iteration":855,"passed_time":10.94539952,"remaining_time":1.841282162},
{"learn":[0.2328087505],"iteration":856,"passed_time":10.95786089,"remaining_time":1.828441198},
{"learn":[0.2326549929],"iteration":857,"passed_time":10.97024979,"remaining_time":1.815589125},
{"learn":[0.2325289748],"iteration":858,"passed_time":10.98423421,"remaining_time":1.803000027},
{"learn":[0.2323658297],"iteration":859,"passed_time":10.99835242,"remaining_time":1.790429463},
{"learn":[0.2322878346],"iteration":860,"passed_time":11.01190552,"remaining_time":1.777764073},
{"learn":[0.2322706759],"iteration":861,"passed_time":11.02407228,"remaining_time":1.764874681},
{"learn":[0.2319170314],"iteration":862,"passed_time":11.03686508,"remaining_time":1.752086345},
{"learn":[0.2314876591],"iteration":863,"passed_time":11.04896697,"remaining_time":1.739189245},
{"learn":[0.2314706689],"iteration":864,"passed_time":11.0604875,"remaining_time":1.726203251},
{"learn":[0.2313269014],"iteration":865,"passed_time":11.07252857,"remaining_time":1.713301187},
{"learn":[0.2310802386],"iteration":866,"passed_time":11.08421807,"remaining_time":1.700347178},
{"learn":[0.230922217],"iteration":867,"passed_time":11.09626355,"remaining_time":1.687450218},
{"learn":[0.2305397773],"iteration":868,"passed_time":11.10853004,"remaining_time":1.674588533},
{"learn":[0.2302399424],"iteration":869,"passed_time":11.1216018,"remaining_time":1.661848545},
{"learn":[0.2300116239],"iteration":870,"passed_time":11.1346917,"remaining_time":1.649110482},
{"learn":[0.2298387371],"iteration":871,"passed_time":11.14695972,"remaining_time":1.636250968},
{"learn":[0.2296442788],"iteration":872,"passed_time":11.16789533,"remaining_time":1.62465373},
{"learn":[0.2292797864],"iteration":873,"passed_time":11.18578451,"remaining_time":1.612595937},
{"learn":[0.2290245424],"iteration":874,"passed_time":11.19955726,"remaining_time":1.599936751},
{"learn":[0.2289006187],"iteration":875,"passed_time":11.21180948,"remaining_time":1.58705979},
{"learn":[0.2287034482],"iteration":876,"passed_time":11.22685017,"remaining_time":1.574575338},
{"learn":[0.2284981731],"iteration":877,"passed_time":11.23889241,"remaining_time":1.561668422},
{"learn":[0.2282067715],"iteration":878,"passed_time":11.25321001,"remaining_time":1.549076691},
{"learn":[0.2279328576],"iteration":879,"passed_time":11.26997157,"remaining_time":1.536814306},
{"learn":[0.2276335774],"iteration":880,"passed_time":11.28300741,"remaining_time":1.524038459},
{"learn":[0.2276150728],"iteration":881,"passed_time":11.29460182,"remaining_time":1.511069177},
{"learn":[0.2275986253],"iteration":882,"passed_time":11.30621476,"remaining_time":1.498105466},
{"learn":[0.2275841706],"iteration":883,"passed_time":11.3176318,"remaining_time":1.485119105},
{"learn":[0.2273864959],"iteration":884,"passed_time":11.32953451,"remaining_time":1.4721994},
{"learn":[0.2272848658],"iteration":885,"passed_time":11.34125904,"remaining_time":1.459259064},
{"learn":[0.2272546587],"iteration":886,"passed_time":11.35287467,"remaining_time":1.446307596},
{"learn":[0.227239018],"iteration":887,"passed_time":11.36428274,"remaining_time":1.433332958},
{"learn":[0.2270732802],"iteration":888,"passed_time":11.37623586,"remaining_time":1.420429899},
{"learn":[0.2269089834],"iteration":889,"passed_time":11.38824917,"remaining_time":1.407536414},
{"learn":[0.2267024655],"iteration":890,"passed_time":11.40030512,"remaining_time":1.394650121},
{"learn":[0.2266724894],"iteration":891,"passed_time":11.41247231,"remaining_time":1.381779159},
{"learn":[0.2262480373],"iteration":892,"passed_time":11.42465908,"remaining_time":1.368912118},
{"learn":[0.2258824867],"iteration":893,"passed_time":11.43703613,"remaining_time":1.356069161},
{"learn":[0.225850493],"iteration":894,"passed_time":11.44903672,"remaining_time":1.343183079},
{"learn":[0.2257392295],"iteration":895,"passed_time":11.46089983,"remaining_time":1.330283016},
{"learn":[0.2255162706],"iteration":896,"passed_time":11.473144,"remaining_time":1.317429022},
{"learn":[0.225314967],"iteration":897,"passed_time":11.48515756,"remaining_time":1.304550191},
{"learn":[0.2249845322],"iteration":898,"passed_time":11.4972646,"remaining_time":1.291683787},
{"learn":[0.2247135054],"iteration":899,"passed_time":11.5098705,"remaining_time":1.2788745},
{"learn":[0.2245371847],"iteration":900,"passed_time":11.52224283,"remaining_time":1.266040001},
{"learn":[0.2245233178],"iteration":901,"passed_time":11.53431306,"remaining_time":1.253173702},
{"learn":[0.2243563814],"iteration":902,"passed_time":11.54654456,"remaining_time":1.240326492},
{"learn":[0.2243242049],"iteration":903,"passed_time":11.55816213,"remaining_time":1.227415448},
{"learn":[0.2240938082],"iteration":904,"passed_time":11.57086498,"remaining_time":1.214621185},
{"learn":[0.2239597007],"iteration":905,"passed_time":11.58330297,"remaining_time":1.201799646},
{"learn":[0.2238642396],"iteration":906,"passed_time":11.59535207,"remaining_time":1.188939076},
{"learn":[0.2234449569],"iteration":907,"passed_time":11.60821715,"remaining_time":1.176162971},
{"learn":[0.2233099727],"iteration":908,"passed_time":11.62036467,"remaining_time":1.163314834},
{"learn":[0.2232954046],"iteration":909,"passed_time":11.63197131,"remaining_time":1.150414745},
{"learn":[0.2232823158],"iteration":910,"passed_time":11.64467289,"remaining_time":1.137624465},
{"learn":[0.2232439442],"iteration":911,"passed_time":11.65646051,"remaining_time":1.124746189},
{"learn":[0.2230617916],"iteration":912,"passed_time":11.66915966,"remaining_time":1.111957164},
{"learn":[0.2229281974],"iteration":913,"passed_time":11.68218473,"remaining_time":1.099199001},
{"learn":[0.2226111629],"iteration":914,"passed_time":11.7002606,"remaining_time":1.086909455},
{"learn":[0.2224132959],"iteration":915,"passed_time":11.71621404,"remaining_time":1.074412642},
{"learn":[0.2223792925],"iteration":916,"passed_time":11.72887876,"remaining_time":1.061610618},
{"learn":[0.222363585],"iteration":917,"passed_time":11.74091163,"remaining_time":1.048752455},
{"learn":[0.2221899017],"iteration":918,"passed_time":11.75381848,"remaining_time":1.03597312},
{"learn":[0.222068018],"iteration":919,"passed_time":11.77299075,"remaining_time":1.023738326},
{"learn":[0.221863732],"iteration":920,"passed_time":11.78847623,"remaining_time":1.011172228},
{"learn":[0.221711792],"iteration":921,"passed_time":11.80043422,"remaining_time":0.9983013762},
{"learn":[0.2215234114],"iteration":922,"passed_time":11.81309731,"remaining_time":0.9854913248},
{"learn":[0.2215062242],"iteration":923,"passed_time":11.82532384,"remaining_time":0.972645684},
{"learn":[0.2212761631],"iteration":924,"passed_time":11.83744115,"remaining_time":0.959792526},
{"learn":[0.2211045023],"iteration":925,"passed_time":11.8496318,"remaining_time":0.9469468175},
{"learn":[0.2208628597],"iteration":926,"passed_time":11.86440485,"remaining_time":0.9343058838},
{"learn":[0.2206099805],"iteration":927,"passed_time":11.8768246,"remaining_time":0.9214777708},
{"learn":[0.2203844573],"iteration":928,"passed_time":11.88904301,"remaining_time":0.9086351489},
{"learn":[0.2201809505],"iteration":929,"passed_time":11.9007816,"remaining_time":0.8957577548},
{"learn":[0.2199683378],"iteration":930,"passed_time":11.91294991,"remaining_time":0.8829146552},
{"learn":[0.2199138675],"iteration":931,"passed_time":11.92505357,"remaining_time":0.8700682865},
{"learn":[0.2197393225],"iteration":932,"passed_time":11.93747727,"remaining_time":0.8572464923},
{"learn":[0.2195315206],"iteration":933,"passed_time":11.94975327,"remaining_time":0.8444151132},
{"learn":[0.219194854],"iteration":934,"passed_time":11.96217707,"remaining_time":0.8315951971},
{"learn":[0.2189672342],"iteration":935,"passed_time":11.97392025,"remaining_time":0.8187295899},
{"learn":[0.2189513876],"iteration":936,"passed_time":11.9854268,"remaining_time":0.805850468},
{"learn":[0.2188083324],"iteration":937,"passed_time":11.9971349,"remaining_time":0.7929875944},
{"learn":[0.2186428133],"iteration":938,"passed_time":12.00892026,"remaining_time":0.7801322002},
{"learn":[0.2185484467],"iteration":939,"passed_time":12.02059357,"remaining_time":0.7672719297},
{"learn":[0.2183791987],"iteration":940,"passed_time":12.03321923,"remaining_time":0.7544738943},
{"learn":[0.2181755978],"iteration":941,"passed_time":12.04585053,"remaining_time":0.7416765718},
{"learn":[0.2179552613],"iteration":942,"passed_time":12.05923169,"remaining_time":0.7289249269},
{"learn":[0.2179093536],"iteration":943,"passed_time":12.07355078,"remaining_time":0.7162275887},
{"learn":[0.2177651973],"iteration":944,"passed_time":12.08647897,"remaining_time":0.703445866},
{"learn":[0.2174733495],"iteration":945,"passed_time":12.09851466,"remaining_time":0.6906128876},
{"learn":[0.2171524588],"iteration":946,"passed_time":12.11088359,"remaining_time":0.677800243},
{"learn":[0.2168899525],"iteration":947,"passed_time":12.12286396,"remaining_time":0.6649672213},
{"learn":[0.216739358],"iteration":948,"passed_time":12.13456793,"remaining_time":0.6521211428},
{"learn":[0.2165597867],"iteration":949,"passed_time":12.14660492,"remaining_time":0.6392949959},
{"learn":[0.2164227221],"iteration":950,"passed_time":12.15858887,"remaining_time":0.6264677757},
{"learn":[0.2163912896],"iteration":951,"passed_time":12.17103961,"remaining_time":0.6136658627},
{"learn":[0.2163056076],"iteration":952,"passed_time":12.18309808,"remaining_time":0.6008453408},
{"learn":[0.2161161198],"iteration":953,"passed_time":12.19604755,"remaining_time":0.5880693787},
{"learn":[0.2157983149],"iteration":954,"passed_time":12.21182135,"remaining_time":0.5754261371},
{"learn":[0.2157846608],"iteration":955,"passed_time":12.23157243,"remaining_time":0.5629594005},
{"learn":[0.2155537223],"iteration":956,"passed_time":12.24504159,"remaining_time":0.5501951811},
{"learn":[0.2153712796],"iteration":957,"passed_time":12.25737364,"remaining_time":0.5373796379},
{"learn":[0.2149626056],"iteration":958,"passed_time":12.26988206,"remaining_time":0.524572643},
{"learn":[0.2146971136],"iteration":959,"passed_time":12.2827112,"remaining_time":0.5117796334},
{"learn":[0.2146346025],"iteration":960,"passed_time":12.29593319,"remaining_time":0.4990024918},
{"learn":[0.2144281952],"iteration":961,"passed_time":12.31036661,"remaining_time":0.4862722779},
{"learn":[0.2142053744],"iteration":962,"passed_time":12.32498035,"remaining_time":0.4735454546},
{"learn":[0.2139737942],"iteration":963,"passed_time":12.33698709,"remaining_time":0.4607173604},
{"learn":[0.2139621263],"iteration":964,"passed_time":12.34922303,"remaining_time":0.4478992809},
{"learn":[0.2137306209],"iteration":965,"passed_time":12.36120867,"remaining_time":0.4350735971},
{"learn":[0.2135772417],"iteration":966,"passed_time":12.37322586,"remaining_time":0.4222507274},
{"learn":[0.2132805364],"iteration":967,"passed_time":12.38563784,"remaining_time":0.4094425731},
{"learn":[0.2130654737],"iteration":968,"passed_time":12.39759734,"remaining_time":0.396620761},
{"learn":[0.21275268],"iteration":969,"passed_time":12.40994028,"remaining_time":0.3838125861},
{"learn":[0.2126046888],"iteration":970,"passed_time":12.42200651,"remaining_time":0.3709971049},
{"learn":[0.2124273341],"iteration":971,"passed_time":12.43410822,"remaining_time":0.3581841873},
{"learn":[0.2122453206],"iteration":972,"passed_time":12.4458666,"remaining_time":0.3453632047},
{"learn":[0.2119104413],"iteration":973,"passed_time":12.45814695,"remaining_time":0.3325583374},
{"learn":[0.2118942785],"iteration":974,"passed_time":12.46965825,"remaining_time":0.3197348268},
{"learn":[0.211855129],"iteration":975,"passed_time":12.48144682,"remaining_time":0.3069208235},
{"learn":[0.2115760817],"iteration":976,"passed_time":12.4933019,"remaining_time":0.2941104848},
{"learn":[0.2115370613],"iteration":977,"passed_time":12.50503185,"remaining_time":0.281299285},
{"learn":[0.2113619508],"iteration":978,"passed_time":12.51713418,"remaining_time":0.2684982818},
{"learn":[0.211112434],"iteration":979,"passed_time":12.52949328,"remaining_time":0.2557039445},
{"learn":[0.2110882601],"iteration":980,"passed_time":12.54147005,"remaining_time":0.2429030897},
{"learn":[0.2110046209],"iteration":981,"passed_time":12.55350745,"remaining_time":0.2301050246},
{"learn":[0.2109908424],"iteration":982,"passed_time":12.56511775,"remaining_time":0.2173011209},
{"learn":[0.2108710046],"iteration":983,"passed_time":12.57678253,"remaining_time":0.2045005289},
{"learn":[0.2107162743],"iteration":984,"passed_time":12.58854217,"remaining_time":0.1917036879},
{"learn":[0.210527511],"iteration":985,"passed_time":12.60036898,"remaining_time":0.1789099043},
{"learn":[0.2103566947],"iteration":986,"passed_time":12.61206292,"remaining_time":0.1661163303},
{"learn":[0.2102509094],"iteration":987,"passed_time":12.62445771,"remaining_time":0.1533334945},
{"learn":[0.2102119065],"iteration":988,"passed_time":12.6362154,"remaining_time":0.1405443573},
{"learn":[0.2100209618],"iteration":989,"passed_time":12.6481181,"remaining_time":0.1277587687},
{"learn":[0.210008211],"iteration":990,"passed_time":12.65985694,"remaining_time":0.1149734737},
{"learn":[0.2097695988],"iteration":991,"passed_time":12.67214863,"remaining_time":0.102194747},
{"learn":[0.2095688411],"iteration":992,"passed_time":12.68431488,"remaining_time":0.08941611701},
{"learn":[0.2093154611],"iteration":993,"passed_time":12.69700628,"remaining_time":0.076641889},
{"learn":[0.2090254484],"iteration":994,"passed_time":12.70964082,"remaining_time":0.06386754181},
{"learn":[0.2087736368],"iteration":995,"passed_time":12.72421846,"remaining_time":0.05110127894},
{"learn":[0.2086143139],"iteration":996,"passed_time":12.74156976,"remaining_time":0.03833972846},
{"learn":[0.2084441381],"iteration":997,"passed_time":12.75472853,"remaining_time":0.02556057822},
{"learn":[0.2082954606],"iteration":998,"passed_time":12.76782106,"remaining_time":0.01278060166},
{"learn":[0.2081506602],"iteration":999,"passed_time":12.77998335,"remaining_time":0}
]}